[
  {
    "box_gacha_deck_ids": [3, 4],
    "box_gacha_id": 2,
    "description": "※各个宝箱可获得的奖品不同。\n※获得宝箱内全部道具后，宝箱的内容将会更换。",
    "id": 12,
    "max_number": 1,
    "min_number": 1
  },
  {
    "box_gacha_deck_ids": [5, 6],
    "box_gacha_id": 2,
    "description": "※各个宝箱可获得的奖品不同。\n※获得宝箱内全部道具后，宝箱的内容将会更换。",
    "id": 13,
    "max_number": 2,
    "min_number": 2
  },
  {
    "box_gacha_deck_ids": [7, 8],
    "box_gacha_id": 2,
    "description": "※各个宝箱可获得的奖品不同。\n※获得宝箱内全部道具后，宝箱的内容将会更换。",
    "id": 14,
    "max_number": 3,
    "min_number": 3
  },
  {
    "box_gacha_deck_ids": [9, 10],
    "box_gacha_id": 2,
    "description": "※各个宝箱可获得的奖品不同。\n※获得宝箱内全部道具后，宝箱的内容将会更换。",
    "id": 15,
    "max_number": 4,
    "min_number": 4
  },
  {
    "box_gacha_deck_ids": [11, 12],
    "box_gacha_id": 2,
    "description": "※各个宝箱可获得的奖品不同。\n※获得宝箱内全部道具后，宝箱的内容将会更换。",
    "id": 16,
    "max_number": 5,
    "min_number": 5
  },
  {
    "box_gacha_deck_ids": [13, 14],
    "box_gacha_id": 2,
    "description": "※宝箱6及其后续宝箱可获得的奖品相同。\n※获得宝箱内全部道具后，宝箱的内容会初始化。",
    "id": 17,
    "max_number": null,
    "min_number": 6
  },
  {
    "box_gacha_deck_ids": [15, 16],
    "box_gacha_id": 3,
    "description": "※各个宝箱可获得的奖品不同。\n※获得宝箱内全部道具后，宝箱的内容将会更换。",
    "id": 18,
    "max_number": 1,
    "min_number": 1
  },
  {
    "box_gacha_deck_ids": [17, 18],
    "box_gacha_id": 3,
    "description": "※各个宝箱可获得的奖品不同。\n※获得宝箱内全部道具后，宝箱的内容将会更换。",
    "id": 19,
    "max_number": 2,
    "min_number": 2
  },
  {
    "box_gacha_deck_ids": [19, 20],
    "box_gacha_id": 3,
    "description": "※各个宝箱可获得的奖品不同。\n※获得宝箱内全部道具后，宝箱的内容将会更换。",
    "id": 20,
    "max_number": 3,
    "min_number": 3
  },
  {
    "box_gacha_deck_ids": [21, 22],
    "box_gacha_id": 3,
    "description": "※各个宝箱可获得的奖品不同。\n※获得宝箱内全部道具后，宝箱的内容将会更换。",
    "id": 21,
    "max_number": 4,
    "min_number": 4
  },
  {
    "box_gacha_deck_ids": [23, 24],
    "box_gacha_id": 3,
    "description": "※各个宝箱可获得的奖品不同。\n※获得宝箱内全部道具后，宝箱的内容将会更换。",
    "id": 22,
    "max_number": 5,
    "min_number": 5
  },
  {
    "box_gacha_deck_ids": [25, 26],
    "box_gacha_id": 3,
    "description": "※宝箱6及其后续宝箱可获得的奖品相同。\n※获得宝箱内全部道具后，宝箱的内容会初始化。",
    "id": 23,
    "max_number": null,
    "min_number": 6
  },
  {
    "box_gacha_deck_ids": [1000000001, 1000000002],
    "box_gacha_id": 1000000001,
    "description": "※各个宝箱可获得的奖品不同。\n※获得宝箱内全部道具后，宝箱的内容将会更换。",
    "id": 1000000001,
    "max_number": 1,
    "min_number": 1
  },
  {
    "box_gacha_deck_ids": [1000000003, 1000000004],
    "box_gacha_id": 1000000001,
    "description": "※各个宝箱可获得的奖品不同。\n※获得宝箱内全部道具后，宝箱的内容将会更换。",
    "id": 1000000002,
    "max_number": 2,
    "min_number": 2
  },
  {
    "box_gacha_deck_ids": [1000000005, 1000000006],
    "box_gacha_id": 1000000001,
    "description": "※各个宝箱可获得的奖品不同。\n※获得宝箱内全部道具后，宝箱的内容将会更换。",
    "id": 1000000003,
    "max_number": 3,
    "min_number": 3
  },
  {
    "box_gacha_deck_ids": [1000000007, 1000000008],
    "box_gacha_id": 1000000001,
    "description": "※各个宝箱可获得的奖品不同。\n※获得宝箱内全部道具后，宝箱的内容将会更换。",
    "id": 1000000004,
    "max_number": 4,
    "min_number": 4
  },
  {
    "box_gacha_deck_ids": [1000000009, 1000000010],
    "box_gacha_id": 1000000001,
    "description": "※各个宝箱可获得的奖品不同。\n※获得宝箱内全部道具后，宝箱的内容将会更换。",
    "id": 1000000005,
    "max_number": 5,
    "min_number": 5
  },
  {
    "box_gacha_deck_ids": [1000000011, 1000000012],
    "box_gacha_id": 1000000001,
    "description": "※各个宝箱可获得的奖品不同。\n※获得宝箱内全部道具后，宝箱的内容将会更换。",
    "id": 1000000006,
    "max_number": null,
    "min_number": 6
  }
]