[
  {
    "category": 1,
    "id": 1,
    "reset_cycle": 1,
    "steps": [
      {
        "count": 2,
        "reward_set_id": 30007
      },
      {
        "count": 5,
        "reward_set_id": 30008
      },
      {
        "count": 8,
        "reward_set_id": 30009
      }
    ]
  },
  {
    "category": 2,
    "id": 2,
    "reset_cycle": 2,
    "steps": [
      {
        "count": 2,
        "reward_set_id": 30011
      },
      {
        "count": 5,
        "reward_set_id": 30054
      },
      {
        "count": 8,
        "reward_set_id": 30079
      },
      {
        "count": 9,
        "reward_set_id": 30123
      }
    ]
  }
]