[
	{
		"id": 0,
		"translated_name": "レスナ",
		"idk_name": "Resna",
		"model_path_hash": "609796561237155831",
		"text": "…………",
		"voice_file": "VOICE_MAIN_001_500_01065",
		"still_path_hash": "6580594669171159823",
		"speech_balloon_type_id": 780292254
	},
	{
		"id": 1,
		"translated_name": "ミミ",
		"idk_name": "Mimi",
		"model_path_hash": "3583184833832830806",
		"text": "…………",
		"voice_file": "VOICE_MAIN_087_500_01066",
		"still_path_hash": "8751939970242030506",
		"speech_balloon_type_id": 780292254
	},
	{
		"id": 2,
		"translated_name": "レスナ",
		"idk_name": "Resna",
		"model_path_hash": "609796561237155831",
		"text": "あ、あの、ミミちゃん……今のって",
		"voice_file": "VOICE_MAIN_001_500_01067",
		"still_path_hash": "6580594669171159823",
		"speech_balloon_type_id": 780292254
	},
	{
		"id": 3,
		"translated_name": "ミミ",
		"idk_name": "Mimi",
		"model_path_hash": "3583184833832830806",
		"text": "……私の本心を言ったまでよ",
		"voice_file": "VOICE_MAIN_087_500_01068",
		"still_path_hash": "8751939970242030506",
		"speech_balloon_type_id": 780292254
	},
	{
		"id": 4,
		"translated_name": "レスナ",
		"idk_name": "Resna",
		"model_path_hash": "609796561237155831",
		"text": "……本心？",
		"voice_file": "VOICE_MAIN_001_500_01069",
		"still_path_hash": "6580594669171159823",
		"speech_balloon_type_id": 780292254
	},
	{
		"id": 5,
		"translated_name": "ミミ",
		"idk_name": "Mimi",
		"model_path_hash": "3583184833832830806",
		"text": "気に食わないのよ。あなたみたいな、\n努力をしてない人間が同じ場所に立っているのが",
		"voice_file": "VOICE_MAIN_087_500_01070",
		"still_path_hash": "8751939970242030506",
		"speech_balloon_type_id": 780292254
	},
	{
		"id": 6,
		"translated_name": "レスナ",
		"idk_name": "Resna",
		"model_path_hash": "609796561237155831",
		"text": "努力してないなんて……",
		"voice_file": "VOICE_MAIN_001_500_01071",
		"still_path_hash": "6580594669171159823",
		"speech_balloon_type_id": 780292254
	},
	{
		"id": 7,
		"translated_name": "ミミ",
		"idk_name": "Mimi",
		"model_path_hash": "3583184833832830806",
		"text": "だってそうでしょ？　入試も受けずに入ってきた\n推薦組なんだから",
		"voice_file": "VOICE_MAIN_087_500_01072",
		"still_path_hash": "8751939970242030506",
		"speech_balloon_type_id": 780292254
	},
	{
		"id": 8,
		"translated_name": "レスナ",
		"idk_name": "Resna",
		"model_path_hash": "609796561237155831",
		"text": "それは……そうだけど",
		"voice_file": "VOICE_MAIN_001_500_01073",
		"still_path_hash": "6580594669171159823",
		"speech_balloon_type_id": 780292254
	},
	{
		"id": 9,
		"translated_name": "ミミ",
		"idk_name": "Mimi",
		"model_path_hash": "3583184833832830806",
		"text": "推薦を受けるために自分を売り込んだわけでもない。\n調合の才能がずば抜けていたわけでもない",
		"voice_file": "VOICE_MAIN_087_500_01074",
		"still_path_hash": "8751939970242030506",
		"speech_balloon_type_id": 780292254
	},
	{
		"id": 10,
		"translated_name": "ミミ",
		"idk_name": "Mimi",
		"model_path_hash": "3583184833832830806",
		"text": "どこかの誰かの気まぐれで……運だけで\nここに来たってわけでしょ？",
		"voice_file": "VOICE_MAIN_087_500_01075",
		"still_path_hash": "8751939970242030506",
		"speech_balloon_type_id": 780292254
	},
	{
		"id": 11,
		"translated_name": "ミミ",
		"idk_name": "Mimi",
		"model_path_hash": "3583184833832830806",
		"text": "……本当に腹が立つ",
		"voice_file": "VOICE_MAIN_087_500_01076",
		"still_path_hash": "8751939970242030506",
		"speech_balloon_type_id": 780292254
	},
	{
		"id": 12,
		"translated_name": "ミミ",
		"idk_name": "Mimi",
		"model_path_hash": "3583184833832830806",
		"text": "ランターナ学園、錬金術科はね！\n努力して努力して努力して……",
		"voice_file": "VOICE_MAIN_087_500_01077",
		"still_path_hash": "8751939970242030506",
		"speech_balloon_type_id": 780292254
	},
	{
		"id": 13,
		"translated_name": "ミミ",
		"idk_name": "Mimi",
		"model_path_hash": "3583184833832830806",
		"text": "そんな人たちが入試でぶつかって、\nそれでもなお残った人だけが立つのを許される場所！",
		"voice_file": "VOICE_MAIN_087_500_01078",
		"still_path_hash": "8751939970242030506",
		"speech_balloon_type_id": 780292254
	},
	{
		"id": 14,
		"translated_name": "ミミ",
		"idk_name": "Mimi",
		"model_path_hash": "3583184833832830806",
		"text": "なんであなたみたいな人間がいるの？\n錬金術を遊びだと思っているような人間が！",
		"voice_file": "VOICE_MAIN_087_500_01079",
		"still_path_hash": "8751939970242030506",
		"speech_balloon_type_id": 780292254
	},
	{
		"id": 15,
		"translated_name": "レスナ",
		"idk_name": "Resna",
		"model_path_hash": "609796561237155831",
		"text": "あ、遊びだなんて思ってないよ！\n私は本気で錬金術をっ……",
		"voice_file": "VOICE_MAIN_001_500_01080",
		"still_path_hash": "6580594669171159823",
		"speech_balloon_type_id": 780292254
	},
	{
		"id": 16,
		"translated_name": "ミミ",
		"idk_name": "Mimi",
		"model_path_hash": "3583184833832830806",
		"text": "本気？\nあれが、あなたの本気だっていうの？",
		"voice_file": "VOICE_MAIN_087_500_01081",
		"still_path_hash": "8751939970242030506",
		"speech_balloon_type_id": 780292254
	},
	{
		"id": 17,
		"translated_name": "レスナ",
		"idk_name": "Resna",
		"model_path_hash": "609796561237155831",
		"text": "え……",
		"voice_file": "VOICE_MAIN_001_500_01082",
		"still_path_hash": "6580594669171159823",
		"speech_balloon_type_id": 780292254
	},
	{
		"id": 18,
		"translated_name": "ミミ",
		"idk_name": "Mimi",
		"model_path_hash": "3583184833832830806",
		"text": "あなた一人じゃ、\n実技試験は合格できなかったじゃない",
		"voice_file": "VOICE_MAIN_087_500_01083",
		"still_path_hash": "8751939970242030506",
		"speech_balloon_type_id": 780292254
	},
	{
		"id": 19,
		"translated_name": "レスナ",
		"idk_name": "Resna",
		"model_path_hash": "609796561237155831",
		"text": "…………！",
		"voice_file": "VOICE_MAIN_001_500_01084",
		"still_path_hash": "6580594669171159823",
		"speech_balloon_type_id": 780292254
	},
	{
		"id": 20,
		"translated_name": "ミミ",
		"idk_name": "Mimi",
		"model_path_hash": "3583184833832830806",
		"text": "先生や先輩がいなかったら\nあなたは今頃、退学になってたわ！",
		"voice_file": "VOICE_MAIN_087_500_01085",
		"still_path_hash": "8751939970242030506",
		"speech_balloon_type_id": 780292254
	},
	{
		"id": 21,
		"translated_name": "レスナ",
		"idk_name": "Resna",
		"model_path_hash": "609796561237155831",
		"text": "それは……",
		"voice_file": "VOICE_MAIN_001_500_01086",
		"still_path_hash": "6580594669171159823",
		"speech_balloon_type_id": 780292254
	},
	{
		"id": 22,
		"translated_name": "ミミ",
		"idk_name": "Mimi",
		"model_path_hash": "3583184833832830806",
		"text": "……私は認めない。あなたなんかに負けない",
		"voice_file": "VOICE_MAIN_087_500_01087",
		"still_path_hash": "8751939970242030506",
		"speech_balloon_type_id": 780292254
	},
	{
		"id": 23,
		"translated_name": "ミミ",
		"idk_name": "Mimi",
		"model_path_hash": "3583184833832830806",
		"text": "錬金祭で見せつけてやるわ。\n私とあなたの差を",
		"voice_file": "VOICE_MAIN_087_500_01088",
		"still_path_hash": "8751939970242030506",
		"speech_balloon_type_id": 780292254
	},
	{
		"id": 24,
		"translated_name": "レスナ",
		"idk_name": "Resna",
		"model_path_hash": "609796561237155831",
		"text": "私……ミミちゃんに、そんな風に思われてたんだ",
		"voice_file": "VOICE_MAIN_001_500_01089",
		"still_path_hash": "6580594669171159823",
		"speech_balloon_type_id": 780292254
	}
]