[
	{
		"id": 0,
		"translated_name": "レスナ",
		"idk_name": "Resna",
		"model_path_hash": "8643265264907274754",
		"text": "あ、イザナちゃん。そっちはどう？",
		"voice_file": "VOICE_MAIN_001_001_00071",
		"still_path_hash": "3572566872346296899",
		"speech_balloon_type_id": 780292254
	},
	{
		"id": 1,
		"translated_name": "イザナ",
		"idk_name": "Izana",
		"model_path_hash": "3955217441086782382",
		"text": "さすが王都。武器の品揃えも一流だね！",
		"voice_file": "VOICE_MAIN_048_001_00072",
		"still_path_hash": "8711233837385589208",
		"speech_balloon_type_id": 780292254
	},
	{
		"id": 2,
		"translated_name": "レスナ",
		"idk_name": "Resna",
		"model_path_hash": "8643265264907274754",
		"text": "表情が輝かしい。\nイザナちゃんのうちと比べてどう？",
		"voice_file": "VOICE_MAIN_001_001_00073",
		"still_path_hash": "3572566872346296899",
		"speech_balloon_type_id": 780292254
	},
	{
		"id": 3,
		"translated_name": "イザナ",
		"idk_name": "Izana",
		"model_path_hash": "3955217441086782382",
		"text": "いやいや、お父さんの作る武器は\nランターナで一番だから！",
		"voice_file": "VOICE_MAIN_048_001_00074",
		"still_path_hash": "8711233837385589208",
		"speech_balloon_type_id": 780292254
	},
	{
		"id": 4,
		"translated_name": "イザナ",
		"idk_name": "Izana",
		"model_path_hash": "3955217441086782382",
		"text": "……と言いたいけど、王都の鍛冶屋も負けてないよ。\n種類もいっぱいあるしね！",
		"voice_file": "VOICE_MAIN_048_001_00075",
		"still_path_hash": "8711233837385589208",
		"speech_balloon_type_id": 780292254
	},
	{
		"id": 5,
		"translated_name": "イザナ",
		"idk_name": "Izana",
		"model_path_hash": "3955217441086782382",
		"text": "前に来た時は見る余裕がなかったし、\n今度はゆっくり全部のお店回っちゃうんだー！",
		"voice_file": "VOICE_MAIN_048_001_00076",
		"still_path_hash": "8711233837385589208",
		"speech_balloon_type_id": 780292254
	},
	{
		"id": 6,
		"translated_name": "レスナ",
		"idk_name": "Resna",
		"model_path_hash": "8643265264907274754",
		"text": "そっか、騎士試験……",
		"voice_file": "VOICE_MAIN_001_001_00077",
		"still_path_hash": "3572566872346296899",
		"speech_balloon_type_id": 780292254
	},
	{
		"id": 7,
		"translated_name": "イザナ",
		"idk_name": "Izana",
		"model_path_hash": "3955217441086782382",
		"text": "うん、アタシ落ちちゃったから。\nあの時はショックだったなあ",
		"voice_file": "VOICE_MAIN_048_001_00078",
		"still_path_hash": "8711233837385589208",
		"speech_balloon_type_id": 780292254
	},
	{
		"id": 8,
		"translated_name": "レスナ",
		"idk_name": "Resna",
		"model_path_hash": "8643265264907274754",
		"text": "すごく落ち込んでたもんね",
		"voice_file": "VOICE_MAIN_001_001_00079",
		"still_path_hash": "3572566872346296899",
		"speech_balloon_type_id": 780292254
	},
	{
		"id": 9,
		"translated_name": "イザナ",
		"idk_name": "Izana",
		"model_path_hash": "3955217441086782382",
		"text": "でも、レスナちゃんのおかげで吹っ切れたんだ",
		"voice_file": "VOICE_MAIN_048_001_00080",
		"still_path_hash": "8711233837385589208",
		"speech_balloon_type_id": 780292254
	},
	{
		"id": 10,
		"translated_name": "イザナ",
		"idk_name": "Izana",
		"model_path_hash": "3955217441086782382",
		"text": "あの時かけてくれた言葉のおかげで、\nまた頑張ろうって思えたんだよ",
		"voice_file": "VOICE_MAIN_048_001_00081",
		"still_path_hash": "8711233837385589208",
		"speech_balloon_type_id": 780292254
	},
	{
		"id": 11,
		"translated_name": "レスナ",
		"idk_name": "Resna",
		"model_path_hash": "8643265264907274754",
		"text": "え、どれのことだろう……私なんて言ったっけ？",
		"voice_file": "VOICE_MAIN_001_001_00082",
		"still_path_hash": "3572566872346296899",
		"speech_balloon_type_id": 780292254
	},
	{
		"id": 12,
		"translated_name": "イザナ",
		"idk_name": "Izana",
		"model_path_hash": "3955217441086782382",
		"text": "ふふ、教えてあーげない！",
		"voice_file": "VOICE_MAIN_048_001_00083",
		"still_path_hash": "8711233837385589208",
		"speech_balloon_type_id": 780292254
	},
	{
		"id": 13,
		"translated_name": "レスナ",
		"idk_name": "Resna",
		"model_path_hash": "8643265264907274754",
		"text": "えー！　教えてよー！",
		"voice_file": "VOICE_MAIN_001_001_00084",
		"still_path_hash": "3572566872346296899",
		"speech_balloon_type_id": 780292254
	},
	{
		"id": 14,
		"translated_name": "イザナ",
		"idk_name": "Izana",
		"model_path_hash": "3955217441086782382",
		"text": "ほーら、そんなことより、今はお店を回ろうよ！",
		"voice_file": "VOICE_MAIN_048_001_00085",
		"still_path_hash": "8711233837385589208",
		"speech_balloon_type_id": 780292254
	},
	{
		"id": 15,
		"translated_name": "レスナ",
		"idk_name": "Resna",
		"model_path_hash": "8643265264907274754",
		"text": "むう……はぐらかされてる……",
		"voice_file": "VOICE_MAIN_001_001_00086",
		"still_path_hash": "3572566872346296899",
		"speech_balloon_type_id": 780292254
	},
	{
		"id": 16,
		"translated_name": "イザナ",
		"idk_name": "Izana",
		"model_path_hash": "3955217441086782382",
		"text": "それにしても、やっぱ値段はちょっとお高めだよね。\nなかなか買えそうにないよー",
		"voice_file": "VOICE_MAIN_048_001_00087",
		"still_path_hash": "8711233837385589208",
		"speech_balloon_type_id": 780292254
	},
	{
		"id": 17,
		"translated_name": "レスナ",
		"idk_name": "Resna",
		"model_path_hash": "8643265264907274754",
		"text": "ん、何か欲しいものでもあったの？",
		"voice_file": "VOICE_MAIN_001_001_00088",
		"still_path_hash": "3572566872346296899",
		"speech_balloon_type_id": 780292254
	},
	{
		"id": 18,
		"translated_name": "イザナ",
		"idk_name": "Izana",
		"model_path_hash": "3955217441086782382",
		"text": "すぐにってわけじゃないけどね。\n今後のために、色々準備しておきたくて",
		"voice_file": "VOICE_MAIN_048_001_00089",
		"still_path_hash": "8711233837385589208",
		"speech_balloon_type_id": 780292254
	},
	{
		"id": 19,
		"translated_name": "イザナ",
		"idk_name": "Izana",
		"model_path_hash": "3955217441086782382",
		"text": "あらゆるものからレスナちゃんを\n守る騎士としてはね",
		"voice_file": "VOICE_MAIN_048_001_00090",
		"still_path_hash": "8711233837385589208",
		"speech_balloon_type_id": 780292254
	},
	{
		"id": 20,
		"translated_name": "レスナ",
		"idk_name": "Resna",
		"model_path_hash": "8643265264907274754",
		"text": "イザナちゃん……。\nうん、頼りにしてるよ",
		"voice_file": "VOICE_MAIN_001_001_00091",
		"still_path_hash": "3572566872346296899",
		"speech_balloon_type_id": 780292254
	}
]