[
	{
		"id": 0,
		"translated_name": "イザナ",
		"idk_name": "Izana",
		"model_path_hash": "3955217441086782382",
		"text": "……えーっと、お父さんに頼まれたものは\nこれで全部買えたかな？",
		"voice_file": "VOICE_MAIN_048_013_00094",
		"still_path_hash": "8711233837385589208",
		"speech_balloon_type_id": 780292254
	},
	{
		"id": 1,
		"translated_name": "レスナ",
		"idk_name": "Resna",
		"model_path_hash": "8643265264907274754",
		"text": "おじさんのケガのお薬は足りてる？\n必要なら私が調合するから言ってね！",
		"voice_file": "VOICE_MAIN_001_013_00095",
		"still_path_hash": "3572566872346296899",
		"speech_balloon_type_id": 780292254
	},
	{
		"id": 2,
		"translated_name": "イザナ",
		"idk_name": "Izana",
		"model_path_hash": "3955217441086782382",
		"text": "あはは、そんなに心配しなくても大丈夫だって！",
		"voice_file": "VOICE_MAIN_048_013_00096",
		"still_path_hash": "8711233837385589208",
		"speech_balloon_type_id": 780292254
	},
	{
		"id": 3,
		"translated_name": "イザナ",
		"idk_name": "Izana",
		"model_path_hash": "3955217441086782382",
		"text": "そもそも、仕事の最中にケガしたお父さんが\n悪いんだもん",
		"voice_file": "VOICE_MAIN_048_013_00097",
		"still_path_hash": "8711233837385589208",
		"speech_balloon_type_id": 780292254
	},
	{
		"id": 4,
		"translated_name": "イザナ",
		"idk_name": "Izana",
		"model_path_hash": "3955217441086782382",
		"text": "アタシがケガした時なんて、それで一人前の鍛冶屋に\nなれるのかーってカンカンになるのにねー",
		"voice_file": "VOICE_MAIN_048_013_00098",
		"still_path_hash": "8711233837385589208",
		"speech_balloon_type_id": 780292254
	},
	{
		"id": 5,
		"translated_name": "イザナ",
		"idk_name": "Izana",
		"model_path_hash": "3955217441086782382",
		"text": "……まぁ、お父さんの腕が治るまでは\nアタシが店を守るけどね",
		"voice_file": "VOICE_MAIN_048_013_00099",
		"still_path_hash": "8711233837385589208",
		"speech_balloon_type_id": 780292254
	},
	{
		"id": 6,
		"translated_name": "レスナ",
		"idk_name": "Resna",
		"model_path_hash": "8643265264907274754",
		"text": "おじさんには子どもの頃からお世話になってるし\nもしものときは私も手伝うから！",
		"voice_file": "VOICE_MAIN_001_013_00100",
		"still_path_hash": "3572566872346296899",
		"speech_balloon_type_id": 780292254
	},
	{
		"id": 7,
		"translated_name": "イザナ",
		"idk_name": "Izana",
		"model_path_hash": "3955217441086782382",
		"text": "うん。ありがと、レスナちゃん！",
		"voice_file": "VOICE_MAIN_048_013_00101",
		"still_path_hash": "8711233837385589208",
		"speech_balloon_type_id": 780292254
	},
	{
		"id": 8,
		"translated_name": "女性Ａ",
		"idk_name": "",
		"model_path_hash": "0",
		"text": "――ちょっと聞いた？\nまたケンカ騒ぎがあったそうよ",
		"voice_file": "VOICE_MAIN_568_013_00102",
		"still_path_hash": "0",
		"speech_balloon_type_id": 780292254
	},
	{
		"id": 9,
		"translated_name": "女性Ｂ",
		"idk_name": "",
		"model_path_hash": "0",
		"text": "ああ、あの組織が原因でしょ？\nなんて言ったかしら……確か、月影の会？",
		"voice_file": "VOICE_MAIN_569_013_00103",
		"still_path_hash": "0",
		"speech_balloon_type_id": 780292254
	},
	{
		"id": 10,
		"translated_name": "女性Ａ",
		"idk_name": "",
		"model_path_hash": "0",
		"text": "あっちでもこっちでも騒ぎを起こして……\n不安になっちゃうわよねぇ",
		"voice_file": "VOICE_MAIN_568_013_00104",
		"still_path_hash": "0",
		"speech_balloon_type_id": 780292254
	},
	{
		"id": 11,
		"translated_name": "イザナ",
		"idk_name": "Izana",
		"model_path_hash": "3955217441086782382",
		"text": "レスナちゃん、今の聞こえた……？",
		"voice_file": "VOICE_MAIN_048_013_00105",
		"still_path_hash": "8711233837385589208",
		"speech_balloon_type_id": 780292254
	},
	{
		"id": 12,
		"translated_name": "レスナ",
		"idk_name": "Resna",
		"model_path_hash": "8643265264907274754",
		"text": "うん。月影の会って言ってたね",
		"voice_file": "VOICE_MAIN_001_013_00106",
		"still_path_hash": "3572566872346296899",
		"speech_balloon_type_id": 780292254
	},
	{
		"id": 13,
		"translated_name": "レスナ",
		"idk_name": "Resna",
		"model_path_hash": "8643265264907274754",
		"text": "あの人たちの名前をこんな表通りで聞くなんて。\n……何か事件でもあったのかな？",
		"voice_file": "VOICE_MAIN_001_013_00107",
		"still_path_hash": "3572566872346296899",
		"speech_balloon_type_id": 780292254
	},
	{
		"id": 14,
		"translated_name": "イザナ",
		"idk_name": "Izana",
		"model_path_hash": "3955217441086782382",
		"text": "レスナちゃん。\n買い物に付き合ってくれて、ありがとね！",
		"voice_file": "VOICE_MAIN_048_013_00108",
		"still_path_hash": "8711233837385589208",
		"speech_balloon_type_id": 780292254
	},
	{
		"id": 15,
		"translated_name": "レスナ",
		"idk_name": "Resna",
		"model_path_hash": "8643265264907274754",
		"text": "ううん、私もイザナちゃんと話せて楽しかったし。\n……おじさん早く良くなるといいね",
		"voice_file": "VOICE_MAIN_001_013_00109",
		"still_path_hash": "3572566872346296899",
		"speech_balloon_type_id": 780292254
	},
	{
		"id": 16,
		"translated_name": "イザナ",
		"idk_name": "Izana",
		"model_path_hash": "3955217441086782382",
		"text": "もぉ～！　本当にそうだよ～！",
		"voice_file": "VOICE_MAIN_048_013_00110",
		"still_path_hash": "8711233837385589208",
		"speech_balloon_type_id": 780292254
	},
	{
		"id": 17,
		"translated_name": "イザナ",
		"idk_name": "Izana",
		"model_path_hash": "3955217441086782382",
		"text": "お父さんが元気にならないと、\nアタシも家から離れられないんだからっ！",
		"voice_file": "VOICE_MAIN_048_013_00111",
		"still_path_hash": "8711233837385589208",
		"speech_balloon_type_id": 780292254
	},
	{
		"id": 18,
		"translated_name": "レスナ",
		"idk_name": "Resna",
		"model_path_hash": "8643265264907274754",
		"text": "ふふっ、そんなこと言って！\nおじさんのこと心配でたまらないって顔してるよ？",
		"voice_file": "VOICE_MAIN_001_013_00112",
		"still_path_hash": "3572566872346296899",
		"speech_balloon_type_id": 780292254
	},
	{
		"id": 19,
		"translated_name": "イザナ",
		"idk_name": "Izana",
		"model_path_hash": "3955217441086782382",
		"text": "うっ！\nま、まあ……そうなんだけど",
		"voice_file": "VOICE_MAIN_048_013_00113",
		"still_path_hash": "8711233837385589208",
		"speech_balloon_type_id": 780292254
	},
	{
		"id": 20,
		"translated_name": "レスナ",
		"idk_name": "Resna",
		"model_path_hash": "8643265264907274754",
		"text": "家族が大変な時は一緒にいてあげて。\nおじさんも、イザナちゃんを頼りにしてるはずだよ",
		"voice_file": "VOICE_MAIN_001_013_00114",
		"still_path_hash": "3572566872346296899",
		"speech_balloon_type_id": 780292254
	},
	{
		"id": 21,
		"translated_name": "イザナ",
		"idk_name": "Izana",
		"model_path_hash": "3955217441086782382",
		"text": "うん……。\nでもアタシはレスナちゃんのことだって……",
		"voice_file": "VOICE_MAIN_048_013_00115",
		"still_path_hash": "8711233837385589208",
		"speech_balloon_type_id": 780292254
	},
	{
		"id": 22,
		"translated_name": "レスナ",
		"idk_name": "Resna",
		"model_path_hash": "8643265264907274754",
		"text": "…………",
		"voice_file": "VOICE_MAIN_001_013_00116",
		"still_path_hash": "3572566872346296899",
		"speech_balloon_type_id": 780292254
	},
	{
		"id": 23,
		"translated_name": "レスナ",
		"idk_name": "Resna",
		"model_path_hash": "8643265264907274754",
		"text": "イザナちゃん、私なら大丈夫だよ！\n今は、おじさんとお店のことだけ考えて。ねっ？",
		"voice_file": "VOICE_MAIN_001_013_00117",
		"still_path_hash": "3572566872346296899",
		"speech_balloon_type_id": 780292254
	},
	{
		"id": 24,
		"translated_name": "イザナ",
		"idk_name": "Izana",
		"model_path_hash": "3955217441086782382",
		"text": "そうだね……分かった！",
		"voice_file": "VOICE_MAIN_048_013_00118",
		"still_path_hash": "8711233837385589208",
		"speech_balloon_type_id": 780292254
	},
	{
		"id": 25,
		"translated_name": "イザナ",
		"idk_name": "Izana",
		"model_path_hash": "3955217441086782382",
		"text": "じゃあ行くね、レスナちゃん",
		"voice_file": "VOICE_MAIN_048_013_00119",
		"still_path_hash": "8711233837385589208",
		"speech_balloon_type_id": 780292254
	},
	{
		"id": 26,
		"translated_name": "レスナ",
		"idk_name": "Resna",
		"model_path_hash": "8643265264907274754",
		"text": "うん",
		"voice_file": "VOICE_MAIN_001_013_00120",
		"still_path_hash": "3572566872346296899",
		"speech_balloon_type_id": 780292254
	},
	{
		"id": 27,
		"translated_name": "イザナ",
		"idk_name": "Izana",
		"model_path_hash": "3955217441086782382",
		"text": "…………",
		"voice_file": "VOICE_MAIN_048_013_00121",
		"still_path_hash": "8711233837385589208",
		"speech_balloon_type_id": 780292254
	},
	{
		"id": 28,
		"translated_name": "レスナ",
		"idk_name": "Resna",
		"model_path_hash": "8643265264907274754",
		"text": "…………",
		"voice_file": "VOICE_MAIN_001_013_00122",
		"still_path_hash": "3572566872346296899",
		"speech_balloon_type_id": 780292254
	},
	{
		"id": 29,
		"translated_name": "イザナ",
		"idk_name": "Izana",
		"model_path_hash": "3955217441086782382",
		"text": "キ、キリがないから本当に行くね",
		"voice_file": "VOICE_MAIN_048_013_00123",
		"still_path_hash": "8711233837385589208",
		"speech_balloon_type_id": 780292254
	},
	{
		"id": 30,
		"translated_name": "レスナ",
		"idk_name": "Resna",
		"model_path_hash": "0",
		"text": "（……本当は、イザナちゃんがいないのは心細い。\n　でも、いつまでも甘えるわけにはいかないから）",
		"voice_file": "VOICE_MAIN_001_013_00124",
		"still_path_hash": "3572566872346296899",
		"speech_balloon_type_id": 780292254
	},
	{
		"id": 31,
		"translated_name": "レスナ",
		"idk_name": "Resna",
		"model_path_hash": "0",
		"text": "（私も、もっと頑張らなくちゃ！）",
		"voice_file": "VOICE_MAIN_001_013_00125",
		"still_path_hash": "3572566872346296899",
		"speech_balloon_type_id": 780292254
	}
]