[
	{
		"id": 0,
		"localized_name": "艾蓮",
		"romanized_name": "Eren",
		"model_path_hash": "6792774824536619778",
		"text": "嗚……嗚……",
		"voice_file": "VOICE_MAIN_085_500_01675",
		"still_path_hash": "8665281077133803696",
		"speech_balloon_type_id": 780292254
	},
	{
		"id": 1,
		"localized_name": "艾蓮",
		"romanized_name": "Eren",
		"model_path_hash": "0",
		"text": "（我本來就知道，自己跟任何人都處不來，\n　因為我的力量，會讓他人遠離我。）",
		"voice_file": "VOICE_MAIN_085_500_01676",
		"still_path_hash": "8665281077133803696",
		"speech_balloon_type_id": 780292254
	},
	{
		"id": 2,
		"localized_name": "艾蓮",
		"romanized_name": "Eren",
		"model_path_hash": "0",
		"text": "（我又要變成孤單一個人了，\n　就像離開自警團那時一樣……）",
		"voice_file": "VOICE_MAIN_085_500_01677",
		"still_path_hash": "8665281077133803696",
		"speech_balloon_type_id": 780292254
	},
	{
		"id": 3,
		"localized_name": "蘿樂娜",
		"romanized_name": "Rorona",
		"model_path_hash": "8435698775993103850",
		"text": "艾蓮。",
		"voice_file": "VOICE_MAIN_018_500_01678",
		"still_path_hash": "7481549006415353290",
		"speech_balloon_type_id": 780292254
	},
	{
		"id": 4,
		"localized_name": "艾蓮",
		"romanized_name": "Eren",
		"model_path_hash": "6792774824536619778",
		"text": "蘿樂娜、學姐……",
		"voice_file": "VOICE_MAIN_085_500_01679",
		"still_path_hash": "8665281077133803696",
		"speech_balloon_type_id": 780292254
	},
	{
		"id": 5,
		"localized_name": "蘿樂娜",
		"romanized_name": "Rorona",
		"model_path_hash": "8435698775993103850",
		"text": "我找妳找很久了耶，妳為什麼要逃跑呢？",
		"voice_file": "VOICE_MAIN_018_500_01680",
		"still_path_hash": "7481549006415353290",
		"speech_balloon_type_id": 780292254
	},
	{
		"id": 6,
		"localized_name": "艾蓮",
		"romanized_name": "Eren",
		"model_path_hash": "6792774824536619778",
		"text": "因為……",
		"voice_file": "VOICE_MAIN_085_500_01681",
		"still_path_hash": "8665281077133803696",
		"speech_balloon_type_id": 780292254
	},
	{
		"id": 7,
		"localized_name": "艾蓮",
		"romanized_name": "Eren",
		"model_path_hash": "6792774824536619778",
		"text": "我嚇到了大家……也嚇到妳……",
		"voice_file": "VOICE_MAIN_085_500_01682",
		"still_path_hash": "8665281077133803696",
		"speech_balloon_type_id": 780292254
	},
	{
		"id": 8,
		"localized_name": "蘿樂娜",
		"romanized_name": "Rorona",
		"model_path_hash": "8435698775993103850",
		"text": "我可以問問詳細原因嗎？",
		"voice_file": "VOICE_MAIN_018_500_01683",
		"still_path_hash": "7481549006415353290",
		"speech_balloon_type_id": 780292254
	},
	{
		"id": 9,
		"localized_name": "艾蓮",
		"romanized_name": "Eren",
		"model_path_hash": "0",
		"text": "…………",
		"voice_file": "VOICE_MAIN_085_500_01684",
		"still_path_hash": "8665281077133803696",
		"speech_balloon_type_id": 780292254
	},
	{
		"id": 10,
		"localized_name": "蘿樂娜",
		"romanized_name": "Rorona",
		"model_path_hash": "8435698775993103850",
		"text": "我想要更了解妳。",
		"voice_file": "VOICE_MAIN_018_500_01685",
		"still_path_hash": "7481549006415353290",
		"speech_balloon_type_id": 780292254
	},
	{
		"id": 11,
		"localized_name": "艾蓮",
		"romanized_name": "Eren",
		"model_path_hash": "6792774824536619778",
		"text": "……我知道了。",
		"voice_file": "VOICE_MAIN_085_500_01686",
		"still_path_hash": "8665281077133803696",
		"speech_balloon_type_id": 780292254
	},
	{
		"id": 12,
		"localized_name": "蘿樂娜",
		"romanized_name": "Rorona",
		"model_path_hash": "8435698775993103850",
		"text": "為了不嚇到人，而在暗地裡活動嗎……",
		"voice_file": "VOICE_MAIN_018_500_01687",
		"still_path_hash": "7481549006415353290",
		"speech_balloon_type_id": 780292254
	},
	{
		"id": 13,
		"localized_name": "艾蓮",
		"romanized_name": "Eren",
		"model_path_hash": "6792774824536619778",
		"text": "是的……從幾年前我辭掉自警團的工作時開始……",
		"voice_file": "VOICE_MAIN_085_500_01688",
		"still_path_hash": "8665281077133803696",
		"speech_balloon_type_id": 780292254
	},
	{
		"id": 14,
		"localized_name": "艾蓮",
		"romanized_name": "Eren",
		"model_path_hash": "6792774824536619778",
		"text": "受到推薦後，我想對自警活動也有幫助，\n於是進了鍊金術科，繼續進行自警活動。",
		"voice_file": "VOICE_MAIN_085_500_01689",
		"still_path_hash": "8665281077133803696",
		"speech_balloon_type_id": 780292254
	},
	{
		"id": 15,
		"localized_name": "蘿樂娜",
		"romanized_name": "Rorona",
		"model_path_hash": "8435698775993103850",
		"text": "所以，妳才經常沒來上課啊……\n妳一定連放學後都在活動吧？",
		"voice_file": "VOICE_MAIN_018_500_01690",
		"still_path_hash": "7481549006415353290",
		"speech_balloon_type_id": 780292254
	},
	{
		"id": 16,
		"localized_name": "蘿樂娜",
		"romanized_name": "Rorona",
		"model_path_hash": "8435698775993103850",
		"text": "之前在森林裡救了我的人，也是妳對吧？",
		"voice_file": "VOICE_MAIN_018_500_01691",
		"still_path_hash": "7481549006415353290",
		"speech_balloon_type_id": 780292254
	},
	{
		"id": 17,
		"localized_name": "蘿樂娜",
		"romanized_name": "Rorona",
		"model_path_hash": "8435698775993103850",
		"text": "難不成，在那之後妳也經常幫助我？",
		"voice_file": "VOICE_MAIN_018_500_01692",
		"still_path_hash": "7481549006415353290",
		"speech_balloon_type_id": 780292254
	},
	{
		"id": 18,
		"localized_name": "艾蓮",
		"romanized_name": "Eren",
		"model_path_hash": "6792774824536619778",
		"text": "……是。",
		"voice_file": "VOICE_MAIN_085_500_01693",
		"still_path_hash": "8665281077133803696",
		"speech_balloon_type_id": 780292254
	},
	{
		"id": 19,
		"localized_name": "蘿樂娜",
		"romanized_name": "Rorona",
		"model_path_hash": "8435698775993103850",
		"text": "這樣啊。",
		"voice_file": "VOICE_MAIN_018_500_01694",
		"still_path_hash": "7481549006415353290",
		"speech_balloon_type_id": 780292254
	},
	{
		"id": 20,
		"localized_name": "艾蓮",
		"romanized_name": "Eren",
		"model_path_hash": "6792774824536619778",
		"text": "學姐……？",
		"voice_file": "VOICE_MAIN_085_500_01695",
		"still_path_hash": "8665281077133803696",
		"speech_balloon_type_id": 780292254
	},
	{
		"id": 21,
		"localized_name": "蘿樂娜",
		"romanized_name": "Rorona",
		"model_path_hash": "8435698775993103850",
		"text": "對不起我一直沒注意到，\n謝謝妳幫了我好多次。",
		"voice_file": "VOICE_MAIN_018_500_01696",
		"still_path_hash": "7481549006415353290",
		"speech_balloon_type_id": 780292254
	},
	{
		"id": 22,
		"localized_name": "艾蓮",
		"romanized_name": "Eren",
		"model_path_hash": "6792774824536619778",
		"text": "我這種人……不值得妳感謝。",
		"voice_file": "VOICE_MAIN_085_500_01697",
		"still_path_hash": "8665281077133803696",
		"speech_balloon_type_id": 780292254
	},
	{
		"id": 23,
		"localized_name": "蘿樂娜",
		"romanized_name": "Rorona",
		"model_path_hash": "8435698775993103850",
		"text": "別這樣責備自己，艾蓮妳並沒有錯啊。",
		"voice_file": "VOICE_MAIN_018_500_01698",
		"still_path_hash": "7481549006415353290",
		"speech_balloon_type_id": 780292254
	},
	{
		"id": 24,
		"localized_name": "艾蓮",
		"romanized_name": "Eren",
		"model_path_hash": "6792774824536619778",
		"text": "可是……我一直瞞著學姐。",
		"voice_file": "VOICE_MAIN_085_500_01699",
		"still_path_hash": "8665281077133803696",
		"speech_balloon_type_id": 780292254
	},
	{
		"id": 25,
		"localized_name": "艾蓮",
		"romanized_name": "Eren",
		"model_path_hash": "6792774824536619778",
		"text": "而且難得妳約我出來，結果都泡湯了……",
		"voice_file": "VOICE_MAIN_085_500_01700",
		"still_path_hash": "8665281077133803696",
		"speech_balloon_type_id": 780292254
	},
	{
		"id": 26,
		"localized_name": "蘿樂娜",
		"romanized_name": "Rorona",
		"model_path_hash": "8435698775993103850",
		"text": "這種事妳不用在意，\n要是想出門，隨時都可以走啊。",
		"voice_file": "VOICE_MAIN_018_500_01701",
		"still_path_hash": "7481549006415353290",
		"speech_balloon_type_id": 780292254
	},
	{
		"id": 27,
		"localized_name": "蘿樂娜",
		"romanized_name": "Rorona",
		"model_path_hash": "8435698775993103850",
		"text": "看是等下次放假，還是下下次，\n我們再一起出門吧？",
		"voice_file": "VOICE_MAIN_018_500_01702",
		"still_path_hash": "7481549006415353290",
		"speech_balloon_type_id": 780292254
	},
	{
		"id": 28,
		"localized_name": "艾蓮",
		"romanized_name": "Eren",
		"model_path_hash": "6792774824536619778",
		"text": "咦……",
		"voice_file": "VOICE_MAIN_085_500_01703",
		"still_path_hash": "8665281077133803696",
		"speech_balloon_type_id": 780292254
	},
	{
		"id": 29,
		"localized_name": "艾蓮",
		"romanized_name": "Eren",
		"model_path_hash": "6792774824536619778",
		"text": "妳……願意再次邀請我嗎？\n就算……就算我是這麼可怕的人……",
		"voice_file": "VOICE_MAIN_085_500_01704",
		"still_path_hash": "8665281077133803696",
		"speech_balloon_type_id": 780292254
	},
	{
		"id": 30,
		"localized_name": "蘿樂娜",
		"romanized_name": "Rorona",
		"model_path_hash": "8435698775993103850",
		"text": "那當然囉。\n的確，我是有點嚇到啦，但是……",
		"voice_file": "VOICE_MAIN_018_500_01705",
		"still_path_hash": "7481549006415353290",
		"speech_balloon_type_id": 780292254
	},
	{
		"id": 31,
		"localized_name": "蘿樂娜",
		"romanized_name": "Rorona",
		"model_path_hash": "8435698775993103850",
		"text": "我知道妳其實是個溫柔又為人著想的孩子啊。",
		"voice_file": "VOICE_MAIN_018_500_01706",
		"still_path_hash": "7481549006415353290",
		"speech_balloon_type_id": 780292254
	},
	{
		"id": 32,
		"localized_name": "艾蓮",
		"romanized_name": "Eren",
		"model_path_hash": "6792774824536619778",
		"text": "學姐……嗚嗚……",
		"voice_file": "VOICE_MAIN_085_500_01707",
		"still_path_hash": "8665281077133803696",
		"speech_balloon_type_id": 780292254
	},
	{
		"id": 33,
		"localized_name": "艾蓮",
		"romanized_name": "Eren",
		"model_path_hash": "6792774824536619778",
		"text": "不好意思……讓妳看到了我難堪的一面。",
		"voice_file": "VOICE_MAIN_085_500_01708",
		"still_path_hash": "8665281077133803696",
		"speech_balloon_type_id": 780292254
	},
	{
		"id": 34,
		"localized_name": "蘿樂娜",
		"romanized_name": "Rorona",
		"model_path_hash": "8435698775993103850",
		"text": "沒事的！妳別介意。",
		"voice_file": "VOICE_MAIN_018_500_01709",
		"still_path_hash": "7481549006415353290",
		"speech_balloon_type_id": 780292254
	},
	{
		"id": 35,
		"localized_name": "蘿樂娜",
		"romanized_name": "Rorona",
		"model_path_hash": "8435698775993103850",
		"text": "該不會妳不願意加入鍊金術社，\n也是擔心和大家處不來吧？",
		"voice_file": "VOICE_MAIN_018_500_01710",
		"still_path_hash": "7481549006415353290",
		"speech_balloon_type_id": 780292254
	},
	{
		"id": 36,
		"localized_name": "艾蓮",
		"romanized_name": "Eren",
		"model_path_hash": "6792774824536619778",
		"text": "是的……",
		"voice_file": "VOICE_MAIN_085_500_01711",
		"still_path_hash": "8665281077133803696",
		"speech_balloon_type_id": 780292254
	},
	{
		"id": 37,
		"localized_name": "蘿樂娜",
		"romanized_name": "Rorona",
		"model_path_hash": "8435698775993103850",
		"text": "我想鍊金術社的大家，應該也都跟我一樣喔。",
		"voice_file": "VOICE_MAIN_018_500_01712",
		"still_path_hash": "7481549006415353290",
		"speech_balloon_type_id": 780292254
	},
	{
		"id": 38,
		"localized_name": "艾蓮",
		"romanized_name": "Eren",
		"model_path_hash": "6792774824536619778",
		"text": "咦？",
		"voice_file": "VOICE_MAIN_085_500_01713",
		"still_path_hash": "8665281077133803696",
		"speech_balloon_type_id": 780292254
	},
	{
		"id": 39,
		"localized_name": "蘿樂娜",
		"romanized_name": "Rorona",
		"model_path_hash": "8435698775993103850",
		"text": "我覺得大家都會接納妳的。\n所以，妳要不要加入鍊金術社看看？",
		"voice_file": "VOICE_MAIN_018_500_01714",
		"still_path_hash": "7481549006415353290",
		"speech_balloon_type_id": 780292254
	},
	{
		"id": 40,
		"localized_name": "艾蓮",
		"romanized_name": "Eren",
		"model_path_hash": "6792774824536619778",
		"text": "真的是這樣嗎……",
		"voice_file": "VOICE_MAIN_085_500_01715",
		"still_path_hash": "8665281077133803696",
		"speech_balloon_type_id": 780292254
	},
	{
		"id": 41,
		"localized_name": "蘿樂娜",
		"romanized_name": "Rorona",
		"model_path_hash": "8435698775993103850",
		"text": "沒事的，大家肯定不會拒絕妳的。",
		"voice_file": "VOICE_MAIN_018_500_01716",
		"still_path_hash": "7481549006415353290",
		"speech_balloon_type_id": 780292254
	},
	{
		"id": 42,
		"localized_name": "蘿樂娜",
		"romanized_name": "Rorona",
		"model_path_hash": "8435698775993103850",
		"text": "倒不如說，擅長戰鬥的人反倒搶手喔！",
		"voice_file": "VOICE_MAIN_018_500_01717",
		"still_path_hash": "7481549006415353290",
		"speech_balloon_type_id": 780292254
	},
	{
		"id": 43,
		"localized_name": "蘿樂娜",
		"romanized_name": "Rorona",
		"model_path_hash": "8435698775993103850",
		"text": "尤其是現在正忙著準備對抗賽，\n很多素材都不足，所以大家一定會很歡迎妳的！",
		"voice_file": "VOICE_MAIN_018_500_01718",
		"still_path_hash": "7481549006415353290",
		"speech_balloon_type_id": 780292254
	},
	{
		"id": 44,
		"localized_name": "艾蓮",
		"romanized_name": "Eren",
		"model_path_hash": "6792774824536619778",
		"text": "這樣、啊……那或許可以加入看看。",
		"voice_file": "VOICE_MAIN_085_500_01719",
		"still_path_hash": "8665281077133803696",
		"speech_balloon_type_id": 780292254
	},
	{
		"id": 45,
		"localized_name": "蘿樂娜",
		"romanized_name": "Rorona",
		"model_path_hash": "8435698775993103850",
		"text": "太好了！",
		"voice_file": "VOICE_MAIN_018_500_01720",
		"still_path_hash": "7481549006415353290",
		"speech_balloon_type_id": 780292254
	},
	{
		"id": 46,
		"localized_name": "蘿樂娜",
		"romanized_name": "Rorona",
		"model_path_hash": "8435698775993103850",
		"text": "那就再次請妳多多指教囉，艾蓮。",
		"voice_file": "VOICE_MAIN_018_500_01721",
		"still_path_hash": "7481549006415353290",
		"speech_balloon_type_id": 780292254
	},
	{
		"id": 47,
		"localized_name": "艾蓮",
		"romanized_name": "Eren",
		"model_path_hash": "6792774824536619778",
		"text": "好的，蘿樂娜學姐。",
		"voice_file": "VOICE_MAIN_085_500_01722",
		"still_path_hash": "8665281077133803696",
		"speech_balloon_type_id": 780292254
	}
]