[
	{
		"id": 0,
		"localized_name": "敏敏",
		"romanized_name": "Mimi",
		"model_path_hash": "3583184833832830806",
		"text": "呼……呼……",
		"voice_file": "VOICE_MAIN_087_500_01759",
		"still_path_hash": "8751939970242030506",
		"speech_balloon_type_id": 780292254
	},
	{
		"id": 1,
		"localized_name": "艾蓮",
		"romanized_name": "Eren",
		"model_path_hash": "6792774824536619778",
		"text": "……被包圍了嗎？",
		"voice_file": "VOICE_MAIN_085_500_01760",
		"still_path_hash": "8665281077133803696",
		"speech_balloon_type_id": 780292254
	},
	{
		"id": 2,
		"localized_name": "蘿樂娜",
		"romanized_name": "Rorona",
		"model_path_hash": "8435698775993103850",
		"text": "怎、怎怎麼辦！\n該怎麼突破包圍……",
		"voice_file": "VOICE_MAIN_018_500_01761",
		"still_path_hash": "7481549006415353290",
		"speech_balloon_type_id": 780292254
	},
	{
		"id": 3,
		"localized_name": "蘿樂娜",
		"romanized_name": "Rorona",
		"model_path_hash": "8435698775993103850",
		"text": "要是把這個丟向對手的話……！",
		"voice_file": "VOICE_MAIN_018_500_01762",
		"still_path_hash": "7481549006415353290",
		"speech_balloon_type_id": 780292254
	},
	{
		"id": 4,
		"localized_name": "蘿樂娜",
		"romanized_name": "Rorona",
		"model_path_hash": "0",
		"text": "咦？",
		"voice_file": "VOICE_MAIN_018_500_01763",
		"still_path_hash": "7481549006415353290",
		"speech_balloon_type_id": 780292254
	},
	{
		"id": 5,
		"localized_name": "蕾斯娜",
		"romanized_name": "Resna",
		"model_path_hash": "609796561237155831",
		"text": "蘿、蘿樂娜學姐！\n妳手裡那個是不是已經點燃了！？",
		"voice_file": "VOICE_MAIN_001_500_01764",
		"still_path_hash": "6580594669171159823",
		"speech_balloon_type_id": 780292254
	},
	{
		"id": 6,
		"localized_name": "蘇菲",
		"romanized_name": "Sophie",
		"model_path_hash": "4144575465169653824",
		"text": "慢、慢著！要是在這種地方爆炸，\n會波及到大家的！",
		"voice_file": "VOICE_MAIN_030_500_01765",
		"still_path_hash": "1084051241042702473",
		"speech_balloon_type_id": 780292254
	},
	{
		"id": 7,
		"localized_name": "蘿樂娜",
		"romanized_name": "Rorona",
		"model_path_hash": "8435698775993103850",
		"text": "啊哇哇哇！我不是故意的！\n是開關自己開了！",
		"voice_file": "VOICE_MAIN_018_500_01766",
		"still_path_hash": "7481549006415353290",
		"speech_balloon_type_id": 780292254
	},
	{
		"id": 8,
		"localized_name": "敏敏",
		"romanized_name": "Mimi",
		"model_path_hash": "3583184833832830806",
		"text": "總、總之快往遠處丟！快點！",
		"voice_file": "VOICE_MAIN_087_500_01767",
		"still_path_hash": "8751939970242030506",
		"speech_balloon_type_id": 780292254
	},
	{
		"id": 9,
		"localized_name": "萊莎",
		"romanized_name": "Ryza",
		"model_path_hash": "6177390781563012672",
		"text": "大家快趴下──！",
		"voice_file": "VOICE_MAIN_039_500_01768",
		"still_path_hash": "4032876692581446895",
		"speech_balloon_type_id": 780292254
	},
	{
		"id": 10,
		"localized_name": "蘿樂娜",
		"romanized_name": "Rorona",
		"model_path_hash": "8435698775993103850",
		"text": "哇哇哇哇……我丟！",
		"voice_file": "VOICE_MAIN_018_500_01769",
		"still_path_hash": "7481549006415353290",
		"speech_balloon_type_id": 780292254
	},
	{
		"id": 11,
		"localized_name": "大家",
		"romanized_name": "",
		"model_path_hash": "0",
		"text": "嗚哇啊啊啊啊啊啊啊啊！！！",
		"voice_file": "VOICE_MAIN_001_500_01770",
		"still_path_hash": "0",
		"speech_balloon_type_id": 780292254
	},
	{
		"id": 12,
		"localized_name": "瑪莉",
		"romanized_name": "Marie",
		"model_path_hash": "1543991191416950894",
		"text": "啊哈、哈、哈！炸得真漂亮！",
		"voice_file": "VOICE_MAIN_009_500_01776",
		"still_path_hash": "1729358731240541415",
		"speech_balloon_type_id": 780292254
	},
	{
		"id": 13,
		"localized_name": "瑪麗翁",
		"romanized_name": "Marion",
		"model_path_hash": "2676271994623593349",
		"text": "還真是炸得徹底……\n唉，收拾善後肯定很累……",
		"voice_file": "VOICE_MAIN_025_500_01777",
		"still_path_hash": "5397390121100149522",
		"speech_balloon_type_id": 780292254
	},
	{
		"id": 14,
		"localized_name": "薩絲琪亞",
		"romanized_name": "Saskia",
		"model_path_hash": "8393915555796547279",
		"text": "呵呵呵。總之，所有人似乎都生存下來了。",
		"voice_file": "VOICE_MAIN_050_500_01778",
		"still_path_hash": "3628130916430439847",
		"speech_balloon_type_id": 780292254
	},
	{
		"id": 15,
		"localized_name": "瑪麗翁",
		"romanized_name": "Marion",
		"model_path_hash": "2676271994623593349",
		"text": "不過，兩方隊伍也很難再繼續交戰了吧。",
		"voice_file": "VOICE_MAIN_025_500_01779",
		"still_path_hash": "5397390121100149522",
		"speech_balloon_type_id": 780292254
	},
	{
		"id": 16,
		"localized_name": "瑪麗翁",
		"romanized_name": "Marion",
		"model_path_hash": "2676271994623593349",
		"text": "這次的對抗賽為貓咪隊和熊熊隊平手……\n雙方並列第一名！",
		"voice_file": "VOICE_MAIN_025_500_01780",
		"still_path_hash": "5397390121100149522",
		"speech_balloon_type_id": 780292254
	},
	{
		"id": 17,
		"localized_name": "萊莎",
		"romanized_name": "Ryza",
		"model_path_hash": "6177390781563012672",
		"text": "果然會是這種結果啊。",
		"voice_file": "VOICE_MAIN_039_500_01781",
		"still_path_hash": "4032876692581446895",
		"speech_balloon_type_id": 780292254
	},
	{
		"id": 18,
		"localized_name": "蘿樂娜",
		"romanized_name": "Rorona",
		"model_path_hash": "8435698775993103850",
		"text": "嗚嗚……抱歉。\n我搞砸了……",
		"voice_file": "VOICE_MAIN_018_500_01782",
		"still_path_hash": "7481549006415353290",
		"speech_balloon_type_id": 780292254
	},
	{
		"id": 19,
		"localized_name": "艾蓮",
		"romanized_name": "Eren",
		"model_path_hash": "0",
		"text": "呵……呵呵，啊哈哈哈！",
		"voice_file": "VOICE_MAIN_085_500_01783",
		"still_path_hash": "8665281077133803696",
		"speech_balloon_type_id": 780292254
	},
	{
		"id": 20,
		"localized_name": "艾蓮",
		"romanized_name": "Eren",
		"model_path_hash": "6792774824536619778",
		"text": "啊哈哈，蘿樂娜學姐……妳好狼狽喔。",
		"voice_file": "VOICE_MAIN_085_500_01784",
		"still_path_hash": "8665281077133803696",
		"speech_balloon_type_id": 780292254
	},
	{
		"id": 21,
		"localized_name": "蘿樂娜",
		"romanized_name": "Rorona",
		"model_path_hash": "8435698775993103850",
		"text": "妳、妳也是啊！",
		"voice_file": "VOICE_MAIN_018_500_01785",
		"still_path_hash": "7481549006415353290",
		"speech_balloon_type_id": 780292254
	},
	{
		"id": 22,
		"localized_name": "蘿樂娜/艾蓮",
		"romanized_name": "",
		"model_path_hash": "0",
		"text": "啊哈哈哈哈！",
		"voice_file": "VOICE_MAIN_085_500_01786",
		"still_path_hash": "0",
		"speech_balloon_type_id": 780292254
	},
	{
		"id": 23,
		"localized_name": "萊莎",
		"romanized_name": "Ryza",
		"model_path_hash": "6177390781563012672",
		"text": "啊哈哈！這也算是有個好結局了吧！",
		"voice_file": "VOICE_MAIN_039_500_01788",
		"still_path_hash": "4032876692581446895",
		"speech_balloon_type_id": 780292254
	},
	{
		"id": 24,
		"localized_name": "蘇菲",
		"romanized_name": "Sophie",
		"model_path_hash": "4144575465169653824",
		"text": "平手算是非常好的結果了吧？",
		"voice_file": "VOICE_MAIN_030_500_01789",
		"still_path_hash": "1084051241042702473",
		"speech_balloon_type_id": 780292254
	},
	{
		"id": 25,
		"localized_name": "敏敏",
		"romanized_name": "Mimi",
		"model_path_hash": "3583184833832830806",
		"text": "不過，我們下次會贏的！",
		"voice_file": "VOICE_MAIN_087_500_01790",
		"still_path_hash": "8751939970242030506",
		"speech_balloon_type_id": 780292254
	},
	{
		"id": 26,
		"localized_name": "蕾斯娜",
		"romanized_name": "Resna",
		"model_path_hash": "609796561237155831",
		"text": "好！我們整隊一起為下一次努力吧！",
		"voice_file": "VOICE_MAIN_001_500_01791",
		"still_path_hash": "6580594669171159823",
		"speech_balloon_type_id": 780292254
	},
	{
		"id": 27,
		"localized_name": "女學生A",
		"romanized_name": "",
		"model_path_hash": "0",
		"text": "欸，艾蓮！\n我有看昨天對抗賽的實況轉播喔～！",
		"voice_file": "VOICE_MAIN_594_500_01792",
		"still_path_hash": "0",
		"speech_balloon_type_id": 780292254
	},
	{
		"id": 28,
		"localized_name": "女學生B",
		"romanized_name": "",
		"model_path_hash": "0",
		"text": "妳在賽場上真的好帥！\n我都要變成妳的粉絲了！",
		"voice_file": "VOICE_MAIN_595_500_01793",
		"still_path_hash": "0",
		"speech_balloon_type_id": 780292254
	},
	{
		"id": 29,
		"localized_name": "艾蓮",
		"romanized_name": "Eren",
		"model_path_hash": "6792774824536619778",
		"text": "謝、謝謝妳……",
		"voice_file": "VOICE_MAIN_085_500_01794",
		"still_path_hash": "8665281077133803696",
		"speech_balloon_type_id": 780292254
	},
	{
		"id": 30,
		"localized_name": "女學生A",
		"romanized_name": "",
		"model_path_hash": "0",
		"text": "而且，我以前覺得艾蓮有一點可怕……",
		"voice_file": "VOICE_MAIN_594_500_01795",
		"still_path_hash": "0",
		"speech_balloon_type_id": 780292254
	},
	{
		"id": 31,
		"localized_name": "女學生A",
		"romanized_name": "",
		"model_path_hash": "0",
		"text": "沒想到妳也會像那樣大笑啊！",
		"voice_file": "VOICE_MAIN_594_500_01796",
		"still_path_hash": "0",
		"speech_balloon_type_id": 780292254
	},
	{
		"id": 32,
		"localized_name": "艾蓮",
		"romanized_name": "Eren",
		"model_path_hash": "0",
		"text": "咦？",
		"voice_file": "VOICE_MAIN_085_500_01797",
		"still_path_hash": "8665281077133803696",
		"speech_balloon_type_id": 780292254
	},
	{
		"id": 33,
		"localized_name": "女學生B",
		"romanized_name": "",
		"model_path_hash": "0",
		"text": "啊，妳是說比賽結束之後的那個對嗎？\n呵呵，我覺得她笑起來滿可愛的。",
		"voice_file": "VOICE_MAIN_595_500_01798",
		"still_path_hash": "0",
		"speech_balloon_type_id": 780292254
	},
	{
		"id": 34,
		"localized_name": "女學生A",
		"romanized_name": "",
		"model_path_hash": "0",
		"text": "真的！有種反差感真可愛～",
		"voice_file": "VOICE_MAIN_594_500_01799",
		"still_path_hash": "0",
		"speech_balloon_type_id": 780292254
	},
	{
		"id": 35,
		"localized_name": "艾蓮",
		"romanized_name": "Eren",
		"model_path_hash": "6792774824536619778",
		"text": "是、是嗎……",
		"voice_file": "VOICE_MAIN_085_500_01800",
		"still_path_hash": "8665281077133803696",
		"speech_balloon_type_id": 780292254
	},
	{
		"id": 36,
		"localized_name": "女學生A",
		"romanized_name": "",
		"model_path_hash": "0",
		"text": "掰掰囉！下次再講比賽的事給我們聽吧～",
		"voice_file": "VOICE_MAIN_594_500_01801",
		"still_path_hash": "0",
		"speech_balloon_type_id": 780292254
	},
	{
		"id": 37,
		"localized_name": "艾蓮",
		"romanized_name": "Eren",
		"model_path_hash": "0",
		"text": "啊……",
		"voice_file": "VOICE_MAIN_085_500_01802",
		"still_path_hash": "8665281077133803696",
		"speech_balloon_type_id": 780292254
	},
	{
		"id": 38,
		"localized_name": "蘇菲",
		"romanized_name": "Sophie",
		"model_path_hash": "4144575465169653824",
		"text": "早安！",
		"voice_file": "VOICE_MAIN_030_500_01803",
		"still_path_hash": "1084051241042702473",
		"speech_balloon_type_id": 780292254
	},
	{
		"id": 39,
		"localized_name": "萊莎",
		"romanized_name": "Ryza",
		"model_path_hash": "6177390781563012672",
		"text": "妳還真行耶～一大早就那麼受歡迎。",
		"voice_file": "VOICE_MAIN_039_500_01804",
		"still_path_hash": "4032876692581446895",
		"speech_balloon_type_id": 780292254
	},
	{
		"id": 40,
		"localized_name": "蕾斯娜",
		"romanized_name": "Resna",
		"model_path_hash": "609796561237155831",
		"text": "畢竟艾蓮在對抗賽上大展身手了嘛！",
		"voice_file": "VOICE_MAIN_001_500_01805",
		"still_path_hash": "6580594669171159823",
		"speech_balloon_type_id": 780292254
	},
	{
		"id": 41,
		"localized_name": "敏敏",
		"romanized_name": "Mimi",
		"model_path_hash": "3583184833832830806",
		"text": "我覺得我們的表現也很亮眼啊……\n不過，這次的功績就讓給妳吧。",
		"voice_file": "VOICE_MAIN_087_500_01806",
		"still_path_hash": "8751939970242030506",
		"speech_balloon_type_id": 780292254
	},
	{
		"id": 42,
		"localized_name": "艾蓮",
		"romanized_name": "Eren",
		"model_path_hash": "6792774824536619778",
		"text": "大家……",
		"voice_file": "VOICE_MAIN_085_500_01807",
		"still_path_hash": "8665281077133803696",
		"speech_balloon_type_id": 780292254
	},
	{
		"id": 43,
		"localized_name": "蘿樂娜",
		"romanized_name": "Rorona",
		"model_path_hash": "8435698775993103850",
		"text": "沒事的，大家肯定不會拒絕妳的。",
		"voice_file": "VOICE_MAIN_018_500_01808",
		"still_path_hash": "7481549006415353290",
		"speech_balloon_type_id": 780292254
	},
	{
		"id": 44,
		"localized_name": "蘿樂娜",
		"romanized_name": "Rorona",
		"model_path_hash": "8435698775993103850",
		"text": "我就說會沒事的對吧？",
		"voice_file": "VOICE_MAIN_018_500_01809",
		"still_path_hash": "7481549006415353290",
		"speech_balloon_type_id": 780292254
	},
	{
		"id": 45,
		"localized_name": "艾蓮",
		"romanized_name": "Eren",
		"model_path_hash": "6792774824536619778",
		"text": "……嗯。",
		"voice_file": "VOICE_MAIN_085_500_01810",
		"still_path_hash": "8665281077133803696",
		"speech_balloon_type_id": 780292254
	}
]