[
	{
		"id": 0,
		"localized_name": "蕾斯娜",
		"romanized_name": "Resna",
		"model_path_hash": "0",
		"text": "（消滅泳裝魔巨人後，\n　我們將完成的煙火交給煙火師傅。）",
		"voice_file": "",
		"still_path_hash": "8893018707549421680",
		"speech_balloon_type_id": 780292254
	},
	{
		"id": 1,
		"localized_name": "蕾斯娜",
		"romanized_name": "Resna",
		"model_path_hash": "0",
		"text": "（這樣一來，我們的工作就全部結束了……\n　接下來只要等待煙火大會舉行的時間到來。）",
		"voice_file": "",
		"still_path_hash": "8893018707549421680",
		"speech_balloon_type_id": 780292254
	},
	{
		"id": 2,
		"localized_name": "科洛蒂婭",
		"romanized_name": "Klaudia",
		"model_path_hash": "9134949578979189760",
		"text": "真漂亮……\n好像一朵大大的花變成星星降落了下來。",
		"voice_file": "",
		"still_path_hash": "2138779168953470716",
		"speech_balloon_type_id": 780292254
	},
	{
		"id": 3,
		"localized_name": "瓦萊莉婭",
		"romanized_name": "Valeria",
		"model_path_hash": "7203201562534310700",
		"text": "雖說在海邊看煙火很不錯，\n但從海上抬頭欣賞也別有一番風味呢。",
		"voice_file": "",
		"still_path_hash": "491776654605821708",
		"speech_balloon_type_id": 780292254
	},
	{
		"id": 4,
		"localized_name": "科洛蒂婭",
		"romanized_name": "Klaudia",
		"model_path_hash": "9134949578979189760",
		"text": "是啊。煙火倒映在海面上……\n就好像海裡也在放煙火一樣。",
		"voice_file": "",
		"still_path_hash": "2138779168953470716",
		"speech_balloon_type_id": 780292254
	},
	{
		"id": 5,
		"localized_name": "瓦萊莉婭",
		"romanized_name": "Valeria",
		"model_path_hash": "7203201562534310700",
		"text": "確實很像。\n整個人好像被煙火包圍起來了。",
		"voice_file": "",
		"still_path_hash": "491776654605821708",
		"speech_balloon_type_id": 780292254
	},
	{
		"id": 6,
		"localized_name": "科洛蒂婭",
		"romanized_name": "Klaudia",
		"model_path_hash": "9134949578979189760",
		"text": "呵呵，那樣聽起來有點熱呢。",
		"voice_file": "",
		"still_path_hash": "2138779168953470716",
		"speech_balloon_type_id": 780292254
	},
	{
		"id": 7,
		"localized_name": "顧客A",
		"romanized_name": "",
		"model_path_hash": "0",
		"text": "哇，好美哦！\n我第一次看到這麼漂亮的煙火！",
		"voice_file": "",
		"still_path_hash": "0",
		"speech_balloon_type_id": 780292254
	},
	{
		"id": 8,
		"localized_name": "顧客B",
		"romanized_name": "",
		"model_path_hash": "0",
		"text": "不枉費我大老遠跑來海涅州。\n我肯定這輩子都忘不了這片景色……",
		"voice_file": "",
		"still_path_hash": "0",
		"speech_balloon_type_id": 780292254
	},
	{
		"id": 9,
		"localized_name": "科洛蒂婭",
		"romanized_name": "Klaudia",
		"model_path_hash": "9134949578979189760",
		"text": "我一直很想看看煙火……\n但也很想看到遊客們露出笑容。",
		"voice_file": "",
		"still_path_hash": "2138779168953470716",
		"speech_balloon_type_id": 780292254
	},
	{
		"id": 10,
		"localized_name": "瓦萊莉婭",
		"romanized_name": "Valeria",
		"model_path_hash": "7203201562534310700",
		"text": "煙火盛放，遊客們也笑容滿面……\n今晚的煙火大會可以說是非常成功吧？",
		"voice_file": "",
		"still_path_hash": "491776654605821708",
		"speech_balloon_type_id": 780292254
	},
	{
		"id": 11,
		"localized_name": "科洛蒂婭",
		"romanized_name": "Klaudia",
		"model_path_hash": "9134949578979189760",
		"text": "嗯，那當然囉！",
		"voice_file": "",
		"still_path_hash": "2138779168953470716",
		"speech_balloon_type_id": 780292254
	},
	{
		"id": 12,
		"localized_name": "萊莎",
		"romanized_name": "Ryza",
		"model_path_hash": "4410480006886664052",
		"text": "蕾斯娜，妳看見剛才的煙火了嗎！？\n那是煙火師傅們做的吧？",
		"voice_file": "",
		"still_path_hash": "2610566028649358956",
		"speech_balloon_type_id": 780292254
	},
	{
		"id": 13,
		"localized_name": "蕾斯娜",
		"romanized_name": "Resna",
		"model_path_hash": "5193474962010573828",
		"text": "是啊，那是今晚最壯觀的煙火呢！師傅的手藝真厲害，\n綻放時還能維持原本漂亮的形狀。",
		"voice_file": "",
		"still_path_hash": "8893018707549421680",
		"speech_balloon_type_id": 780292254
	},
	{
		"id": 14,
		"localized_name": "萊莎",
		"romanized_name": "Ryza",
		"model_path_hash": "4410480006886664052",
		"text": "啊，要放下一發了！",
		"voice_file": "",
		"still_path_hash": "2610566028649358956",
		"speech_balloon_type_id": 780292254
	},
	{
		"id": 15,
		"localized_name": "蕾斯娜",
		"romanized_name": "Resna",
		"model_path_hash": "5193474962010573828",
		"text": "哇……好漂亮。\n我好像在做夢一樣……",
		"voice_file": "",
		"still_path_hash": "8893018707549421680",
		"speech_balloon_type_id": 780292254
	},
	{
		"id": 16,
		"localized_name": "羅曼",
		"romanized_name": "Roman",
		"model_path_hash": "2044084852602675005",
		"text": "如我所料，拜託蕾斯娜她們是對的。",
		"voice_file": "",
		"still_path_hash": "2419706081160656678",
		"speech_balloon_type_id": 780292254
	},
	{
		"id": 17,
		"localized_name": "羅曼",
		"romanized_name": "Roman",
		"model_path_hash": "2044084852602675005",
		"text": "如果沒有她們幫忙，我想今晚就沒辦法看到\n這麼美麗的煙火了吧。",
		"voice_file": "",
		"still_path_hash": "2419706081160656678",
		"speech_balloon_type_id": 780292254
	},
	{
		"id": 18,
		"localized_name": "尤娜",
		"romanized_name": "Juna",
		"model_path_hash": "7176586596496405136",
		"text": "是啊。",
		"voice_file": "",
		"still_path_hash": "6403040722015916711",
		"speech_balloon_type_id": 780292254
	},
	{
		"id": 19,
		"localized_name": "羅曼",
		"romanized_name": "Roman",
		"model_path_hash": "2044084852602675005",
		"text": "尤娜，也謝謝妳一直監視著海邊。",
		"voice_file": "",
		"still_path_hash": "2419706081160656678",
		"speech_balloon_type_id": 780292254
	},
	{
		"id": 20,
		"localized_name": "尤娜",
		"romanized_name": "Juna",
		"model_path_hash": "7176586596496405136",
		"text": "不，我只是完成自己的職責而已。",
		"voice_file": "",
		"still_path_hash": "6403040722015916711",
		"speech_balloon_type_id": 780292254
	},
	{
		"id": 21,
		"localized_name": "羅曼",
		"romanized_name": "Roman",
		"model_path_hash": "2044084852602675005",
		"text": "好啦，我的工作也到此告一段落了。\n接下來我就以羅曼的身分好好享受海邊的樂趣吧。",
		"voice_file": "",
		"still_path_hash": "2419706081160656678",
		"speech_balloon_type_id": 780292254
	},
	{
		"id": 22,
		"localized_name": "瓦萊莉婭",
		"romanized_name": "Valeria",
		"model_path_hash": "7203201562534310700",
		"text": "當初有來海涅州真是太好了。\n盡情享受了度假氣氛，這下我也心滿意足了！",
		"voice_file": "",
		"still_path_hash": "491776654605821708",
		"speech_balloon_type_id": 780292254
	},
	{
		"id": 23,
		"localized_name": "科洛蒂婭",
		"romanized_name": "Klaudia",
		"model_path_hash": "9134949578979189760",
		"text": "是啊。我們大家一起創造了很多美好的回憶，\n這可是相當難得的經驗呢。",
		"voice_file": "",
		"still_path_hash": "2138779168953470716",
		"speech_balloon_type_id": 780292254
	},
	{
		"id": 24,
		"localized_name": "萊莎",
		"romanized_name": "Ryza",
		"model_path_hash": "4410480006886664052",
		"text": "無論是海之家、海灘奪旗大賽或是島魚，\n每一個回憶都真的超有趣的──！",
		"voice_file": "",
		"still_path_hash": "2610566028649358956",
		"speech_balloon_type_id": 780292254
	},
	{
		"id": 25,
		"localized_name": "蕾斯娜",
		"romanized_name": "Resna",
		"model_path_hash": "5193474962010573828",
		"text": "我們明年再一起來海邊吧。\n快樂的回憶永遠不嫌多嘛！",
		"voice_file": "",
		"still_path_hash": "8893018707549421680",
		"speech_balloon_type_id": 780292254
	}
]