[
	{
		"id": 0,
		"localized_name": "ミーケ",
		"romanized_name": "Mieke",
		"model_path_hash": "2030382357858859941",
		"text": "さーて、予選が終わり夜になりました！\n本選は翌日からの開始となります！",
		"voice_file": "",
		"still_path_hash": "3240945360405906396",
		"speech_balloon_type_id": 780292254
	},
	{
		"id": 1,
		"localized_name": "ディオーナ",
		"romanized_name": "Diona",
		"model_path_hash": "8362757972503745111",
		"text": "レースは一時中断となりますが、夜も様々な\n出し物があります。ぜひ楽しんでいってください",
		"voice_file": "",
		"still_path_hash": "4555134452802376031",
		"speech_balloon_type_id": 780292254
	},
	{
		"id": 2,
		"localized_name": "ヨハナ",
		"romanized_name": "Johanna",
		"model_path_hash": "6763523268261092223",
		"text": "みんな、予選は勝ち抜いたみたいね。\nま、こんなので私たちが負けるなんて思ってないけど",
		"voice_file": "",
		"still_path_hash": "5625633481186064994",
		"speech_balloon_type_id": 780292254
	},
	{
		"id": 3,
		"localized_name": "ヴァレリア",
		"romanized_name": "Valeria",
		"model_path_hash": "7203201562534310700",
		"text": "うん。鶏肉はもう目の前ってこと。\nどうしよう、もうお腹が空いてきたわ",
		"voice_file": "",
		"still_path_hash": "491776654605821708",
		"speech_balloon_type_id": 780292254
	},
	{
		"id": 4,
		"localized_name": "アンチュ",
		"romanized_name": "Antje",
		"model_path_hash": "1263802190917653320",
		"text": "もう勝った気でいるの……？\n手を抜くつもりはないわ",
		"voice_file": "",
		"still_path_hash": "7101962426125413487",
		"speech_balloon_type_id": 780292254
	},
	{
		"id": 5,
		"localized_name": "レスナ",
		"romanized_name": "Resna",
		"model_path_hash": "5193474962010573828",
		"text": "油断大敵、最後まで気を抜いちゃダメだよヴァレリア！",
		"voice_file": "",
		"still_path_hash": "8893018707549421680",
		"speech_balloon_type_id": 780292254
	},
	{
		"id": 6,
		"localized_name": "ライザ",
		"romanized_name": "Ryza",
		"model_path_hash": "4410480006886664052",
		"text": "あたしたちのことを忘れてもらっちゃ困るよ。\nやるからには１位を目指すからね、クラウディア",
		"voice_file": "",
		"still_path_hash": "2610566028649358956",
		"speech_balloon_type_id": 780292254
	},
	{
		"id": 7,
		"localized_name": "クラウディア",
		"romanized_name": "Klaudia",
		"model_path_hash": "9134949578979189760",
		"text": "もう。賞品に興味なんてないんでしょ、ライザは",
		"voice_file": "",
		"still_path_hash": "2138779168953470716",
		"speech_balloon_type_id": 780292254
	},
	{
		"id": 8,
		"localized_name": "ヨハナ",
		"romanized_name": "Johanna",
		"model_path_hash": "6763523268261092223",
		"text": "みんな好き勝手言ってるけど、１位の座は\n私のものよ！　圧倒的大差で勝ってやるんだから！",
		"voice_file": "",
		"still_path_hash": "5625633481186064994",
		"speech_balloon_type_id": 780292254
	},
	{
		"id": 9,
		"localized_name": "アンチュ",
		"romanized_name": "Antje",
		"model_path_hash": "1263802190917653320",
		"text": "とは言っても、このレース……。\n突拍子もないことばかり起きてる気がする",
		"voice_file": "",
		"still_path_hash": "7101962426125413487",
		"speech_balloon_type_id": 780292254
	},
	{
		"id": 10,
		"localized_name": "ライザ",
		"romanized_name": "Ryza",
		"model_path_hash": "4410480006886664052",
		"text": "ぷにとか、ウサギとかのこと？\n確かに気になるよね",
		"voice_file": "",
		"still_path_hash": "2610566028649358956",
		"speech_balloon_type_id": 780292254
	},
	{
		"id": 11,
		"localized_name": "ヨハナ",
		"romanized_name": "Johanna",
		"model_path_hash": "6763523268261092223",
		"text": "どーせ、盛り上げるためとか言って\nララの奴が何か仕込んでるんでしょ",
		"voice_file": "",
		"still_path_hash": "5625633481186064994",
		"speech_balloon_type_id": 780292254
	},
	{
		"id": 12,
		"localized_name": "ララ",
		"romanized_name": "Lara",
		"model_path_hash": "2405902653278929116",
		"text": "あら、心外ですわ。\nそんな無粋なこと、わたくしはしませんわよ",
		"voice_file": "",
		"still_path_hash": "5932763039454849760",
		"speech_balloon_type_id": 780292254
	},
	{
		"id": 13,
		"localized_name": "レスナ",
		"romanized_name": "Resna",
		"model_path_hash": "5193474962010573828",
		"text": "ララさん！　お仕事お疲れさまです！",
		"voice_file": "",
		"still_path_hash": "8893018707549421680",
		"speech_balloon_type_id": 780292254
	},
	{
		"id": 14,
		"localized_name": "ヨハナ",
		"romanized_name": "Johanna",
		"model_path_hash": "6763523268261092223",
		"text": "あんたの仕業じゃないっていうなら、\nあれはただの事故だったっていうわけ？",
		"voice_file": "",
		"still_path_hash": "5625633481186064994",
		"speech_balloon_type_id": 780292254
	},
	{
		"id": 15,
		"localized_name": "ララ",
		"romanized_name": "Lara",
		"model_path_hash": "2405902653278929116",
		"text": "そうは見えませんわね。\n何者かの企みに違いありませんわ",
		"voice_file": "",
		"still_path_hash": "5932763039454849760",
		"speech_balloon_type_id": 780292254
	},
	{
		"id": 16,
		"localized_name": "ヨハナ",
		"romanized_name": "Johanna",
		"model_path_hash": "6763523268261092223",
		"text": "何者かって……誰よ！",
		"voice_file": "",
		"still_path_hash": "5625633481186064994",
		"speech_balloon_type_id": 780292254
	},
	{
		"id": 17,
		"localized_name": "ララ",
		"romanized_name": "Lara",
		"model_path_hash": "2405902653278929116",
		"text": "こんなことをするのは一人しかいないでしょう。\nクリセルダですわ",
		"voice_file": "",
		"still_path_hash": "5932763039454849760",
		"speech_balloon_type_id": 780292254
	},
	{
		"id": 18,
		"localized_name": "ヨハナ",
		"romanized_name": "Johanna",
		"model_path_hash": "6763523268261092223",
		"text": "あいつが！？　なに考えてるわけ！？\n見かけたらただじゃおかないわ",
		"voice_file": "",
		"still_path_hash": "5625633481186064994",
		"speech_balloon_type_id": 780292254
	},
	{
		"id": 19,
		"localized_name": "ララ",
		"romanized_name": "Lara",
		"model_path_hash": "2405902653278929116",
		"text": "わたくしからも言い聞かせるつもりですわ。\n本選では妨害させませんから、安心しなさいな",
		"voice_file": "",
		"still_path_hash": "5932763039454849760",
		"speech_balloon_type_id": 780292254
	},
	{
		"id": 20,
		"localized_name": "ララ",
		"romanized_name": "Lara",
		"model_path_hash": "2405902653278929116",
		"text": "それよりも、夜の出し物も楽しんでらっしゃい",
		"voice_file": "",
		"still_path_hash": "5932763039454849760",
		"speech_balloon_type_id": 780292254
	},
	{
		"id": 21,
		"localized_name": "ララ",
		"romanized_name": "Lara",
		"model_path_hash": "2405902653278929116",
		"text": "歌姫の歌を聞きながら光で照らされた\n海を眺めるのも、乙なものですわよ",
		"voice_file": "",
		"still_path_hash": "5932763039454849760",
		"speech_balloon_type_id": 780292254
	},
	{
		"id": 22,
		"localized_name": "ライザ",
		"romanized_name": "Ryza",
		"model_path_hash": "4410480006886664052",
		"text": "おお、楽しそう！　行ってみよう、みんな！",
		"voice_file": "",
		"still_path_hash": "2610566028649358956",
		"speech_balloon_type_id": 780292254
	},
	{
		"id": 23,
		"localized_name": "レスナ",
		"romanized_name": "Resna",
		"model_path_hash": "5193474962010573828",
		"text": "はい！　先輩、お供いたします！",
		"voice_file": "",
		"still_path_hash": "8893018707549421680",
		"speech_balloon_type_id": 780292254
	},
	{
		"id": 24,
		"localized_name": "ふたり",
		"romanized_name": "",
		"model_path_hash": "0",
		"text": "……",
		"voice_file": "",
		"still_path_hash": "0",
		"speech_balloon_type_id": 780292254
	}
]