[
	{
		"id": 0,
		"translated_name": "ライザ",
		"idk_name": "Ryza",
		"model_path_hash": "6459971860569016995",
		"text": "クラウディア！",
		"voice_file": "",
		"still_path_hash": "633958553226542878",
		"speech_balloon_type_id": 780292254
	},
	{
		"id": 1,
		"translated_name": "クラウディア",
		"idk_name": "Klaudia",
		"model_path_hash": "5759062853790003980",
		"text": "ライザ？",
		"voice_file": "",
		"still_path_hash": "3889512966648791224",
		"speech_balloon_type_id": 780292254
	},
	{
		"id": 2,
		"translated_name": "ライザ",
		"idk_name": "Ryza",
		"model_path_hash": "6459971860569016995",
		"text": "はあ、はあっ……\nよかったぁ、まだここにいて",
		"voice_file": "",
		"still_path_hash": "633958553226542878",
		"speech_balloon_type_id": 780292254
	},
	{
		"id": 3,
		"translated_name": "クラウディア",
		"idk_name": "Klaudia",
		"model_path_hash": "5759062853790003980",
		"text": "どうしたの、そんなに慌てて。\n何かあった？",
		"voice_file": "",
		"still_path_hash": "3889512966648791224",
		"speech_balloon_type_id": 780292254
	},
	{
		"id": 4,
		"translated_name": "ライザ",
		"idk_name": "Ryza",
		"model_path_hash": "6459971860569016995",
		"text": "クラウディアが出発する前に、\n渡したいものがあって……",
		"voice_file": "",
		"still_path_hash": "633958553226542878",
		"speech_balloon_type_id": 780292254
	},
	{
		"id": 5,
		"translated_name": "ライザ",
		"idk_name": "Ryza",
		"model_path_hash": "6459971860569016995",
		"text": "これ、開けてみて",
		"voice_file": "",
		"still_path_hash": "633958553226542878",
		"speech_balloon_type_id": 780292254
	},
	{
		"id": 6,
		"translated_name": "クラウディア",
		"idk_name": "Klaudia",
		"model_path_hash": "5759062853790003980",
		"text": "……これ、ペンダント？\nでも、どうして同じものが２つあるの？",
		"voice_file": "",
		"still_path_hash": "3889512966648791224",
		"speech_balloon_type_id": 780292254
	},
	{
		"id": 7,
		"translated_name": "ライザ",
		"idk_name": "Ryza",
		"model_path_hash": "6459971860569016995",
		"text": "１つはあたしの。……そしてもう１つは\nクラウディアに持っていてほしい",
		"voice_file": "",
		"still_path_hash": "633958553226542878",
		"speech_balloon_type_id": 780292254
	},
	{
		"id": 8,
		"translated_name": "ライザ",
		"idk_name": "Ryza",
		"model_path_hash": "6459971860569016995",
		"text": "このペンダント、別れた人がまた会えるって\nいわれてる縁結びの鉱石を素材に使ってるんだよ",
		"voice_file": "",
		"still_path_hash": "633958553226542878",
		"speech_balloon_type_id": 780292254
	},
	{
		"id": 9,
		"translated_name": "クラウディア",
		"idk_name": "Klaudia",
		"model_path_hash": "0",
		"text": "…………！",
		"voice_file": "",
		"still_path_hash": "3889512966648791224",
		"speech_balloon_type_id": 780292254
	},
	{
		"id": 10,
		"translated_name": "ライザ",
		"idk_name": "Ryza",
		"model_path_hash": "6459971860569016995",
		"text": "あたしね……本当はクラウディアが\n街を出ていっちゃうのが寂しいんだ",
		"voice_file": "",
		"still_path_hash": "633958553226542878",
		"speech_balloon_type_id": 780292254
	},
	{
		"id": 11,
		"translated_name": "ライザ",
		"idk_name": "Ryza",
		"model_path_hash": "6459971860569016995",
		"text": "でも、クラウディアの……友達の夢は応援したい",
		"voice_file": "",
		"still_path_hash": "633958553226542878",
		"speech_balloon_type_id": 780292254
	},
	{
		"id": 12,
		"translated_name": "クラウディア",
		"idk_name": "Klaudia",
		"model_path_hash": "5759062853790003980",
		"text": "ライザ……",
		"voice_file": "",
		"still_path_hash": "3889512966648791224",
		"speech_balloon_type_id": 780292254
	},
	{
		"id": 13,
		"translated_name": "ライザ",
		"idk_name": "Ryza",
		"model_path_hash": "6459971860569016995",
		"text": "だからまた会おうって約束して！",
		"voice_file": "",
		"still_path_hash": "633958553226542878",
		"speech_balloon_type_id": 780292254
	},
	{
		"id": 14,
		"translated_name": "ライザ",
		"idk_name": "Ryza",
		"model_path_hash": "6459971860569016995",
		"text": "このペンダントは、その証として\nずっと持っていてほしい",
		"voice_file": "",
		"still_path_hash": "633958553226542878",
		"speech_balloon_type_id": 780292254
	},
	{
		"id": 15,
		"translated_name": "クラウディア",
		"idk_name": "Klaudia",
		"model_path_hash": "5759062853790003980",
		"text": "……私だって、ライザと離れるのは寂しいよ",
		"voice_file": "",
		"still_path_hash": "3889512966648791224",
		"speech_balloon_type_id": 780292254
	},
	{
		"id": 16,
		"translated_name": "クラウディア",
		"idk_name": "Klaudia",
		"model_path_hash": "5759062853790003980",
		"text": "だから、帰ってくる。\n……ライザに会いに、必ず帰ってくるから！",
		"voice_file": "",
		"still_path_hash": "3889512966648791224",
		"speech_balloon_type_id": 780292254
	},
	{
		"id": 17,
		"translated_name": "ライザ",
		"idk_name": "Ryza",
		"model_path_hash": "6459971860569016995",
		"text": "約束だよ、クラウディア。\nどこにいても、あたしたちは友達だからね！",
		"voice_file": "",
		"still_path_hash": "633958553226542878",
		"speech_balloon_type_id": 780292254
	},
	{
		"id": 18,
		"translated_name": "クラウディア",
		"idk_name": "Klaudia",
		"model_path_hash": "5759062853790003980",
		"text": "うん！　約束だよ、ライザ！",
		"voice_file": "",
		"still_path_hash": "3889512966648791224",
		"speech_balloon_type_id": 780292254
	},
	{
		"id": 19,
		"translated_name": "パトリツィア",
		"idk_name": "Patricia",
		"model_path_hash": "0",
		"text": "（そっか……レスナさんは気付いてたんだ。\n　あれが縁結びの鉱石だって）",
		"voice_file": "",
		"still_path_hash": "843612410526148402",
		"speech_balloon_type_id": 780292254
	},
	{
		"id": 20,
		"translated_name": "パトリツィア",
		"idk_name": "Patricia",
		"model_path_hash": "0",
		"text": "（離れていても、\n　二人の心はそばにあるように……）",
		"voice_file": "",
		"still_path_hash": "843612410526148402",
		"speech_balloon_type_id": 780292254
	},
	{
		"id": 21,
		"translated_name": "パトリツィア",
		"idk_name": "Patricia",
		"model_path_hash": "0",
		"text": "…………",
		"voice_file": "",
		"still_path_hash": "843612410526148402",
		"speech_balloon_type_id": 780292254
	},
	{
		"id": 22,
		"translated_name": "パトリツィア",
		"idk_name": "Patricia",
		"model_path_hash": "0",
		"text": "（私も……タオさんの役に立ちたいと願うのなら\n　あの人の夢を応援するべきだわ）",
		"voice_file": "",
		"still_path_hash": "843612410526148402",
		"speech_balloon_type_id": 780292254
	},
	{
		"id": 23,
		"translated_name": "パトリツィア",
		"idk_name": "Patricia",
		"model_path_hash": "0",
		"text": "（どんなに寂しくても怖くても……\n　自分の気持ちを素直に伝えなくちゃ）",
		"voice_file": "",
		"still_path_hash": "843612410526148402",
		"speech_balloon_type_id": 780292254
	},
	{
		"id": 24,
		"translated_name": "パトリツィア",
		"idk_name": "Patricia",
		"model_path_hash": "2570807231395549316",
		"text": "私……タオさんの地図を修復したい！",
		"voice_file": "",
		"still_path_hash": "843612410526148402",
		"speech_balloon_type_id": 780292254
	}
]