[
	{
		"id": 0,
		"localized_name": "罗曼",
		"romanized_name": "Roman",
		"model_path_hash": "2044084852602675005",
		"text": "这次人造顶兽事件总算是平息了。多亏大家出力，\n才能最大程度减少了海岸地区的损失。",
		"voice_file": "VOICE_MAIN_049_017_00996",
		"still_path_hash": "2419706081160656678",
		"speech_balloon_type_id": 780292254
	},
	{
		"id": 1,
		"localized_name": "罗曼",
		"romanized_name": "Roman",
		"model_path_hash": "2044084852602675005",
		"text": "针对异邦人的袭击也停止了，\n事情终于告一段落。",
		"voice_file": "VOICE_MAIN_049_017_00997",
		"still_path_hash": "2419706081160656678",
		"speech_balloon_type_id": 780292254
	},
	{
		"id": 2,
		"localized_name": "蕾斯娜",
		"romanized_name": "Resna",
		"model_path_hash": "8643265264907274754",
		"text": "虽然城镇遭到破坏，但幸好没有居民伤亡。",
		"voice_file": "VOICE_MAIN_001_017_00998",
		"still_path_hash": "3572566872346296899",
		"speech_balloon_type_id": 780292254
	},
	{
		"id": 3,
		"localized_name": "约翰娜",
		"romanized_name": "Johanna",
		"model_path_hash": "4318551206560057077",
		"text": "这都得感谢本天才的天才避难引导！\n现在伤也治好了，我会继续活跃的！",
		"voice_file": "VOICE_MAIN_004_017_00999",
		"still_path_hash": "125453364659396444",
		"speech_balloon_type_id": 780292254
	},
	{
		"id": 4,
		"localized_name": "伊札娜",
		"romanized_name": "Izana",
		"model_path_hash": "3955217441086782382",
		"text": "有这个想法是好事，但千万不要勉强自己！",
		"voice_file": "VOICE_MAIN_048_017_01000",
		"still_path_hash": "8711233837385589208",
		"speech_balloon_type_id": 780292254
	},
	{
		"id": 5,
		"localized_name": "罗曼",
		"romanized_name": "Roman",
		"model_path_hash": "2044084852602675005",
		"text": "但诡异的是……\n自那之后，极夜的炼金党就销声匿迹了。",
		"voice_file": "VOICE_MAIN_049_017_01001",
		"still_path_hash": "2419706081160656678",
		"speech_balloon_type_id": 780292254
	},
	{
		"id": 6,
		"localized_name": "瓦莱莉娅",
		"romanized_name": "Valeria",
		"model_path_hash": "4979147540429202173",
		"text": "最后的据点是在诺特州的大森林里对吧？\n他们会不会去那里了？",
		"voice_file": "VOICE_MAIN_002_017_01002",
		"still_path_hash": "7558252374860649663",
		"speech_balloon_type_id": 780292254
	},
	{
		"id": 7,
		"localized_name": "蕾斯娜",
		"romanized_name": "Resna",
		"model_path_hash": "8643265264907274754",
		"text": "最好是能在他们动手前我们先主动出击……",
		"voice_file": "VOICE_MAIN_001_017_01003",
		"still_path_hash": "3572566872346296899",
		"speech_balloon_type_id": 780292254
	},
	{
		"id": 8,
		"localized_name": "瓦尔特",
		"romanized_name": "Walther",
		"model_path_hash": "8090265573840748859",
		"text": "克莉赛尔达，前几天的战斗记录整理好了，\n这是分析结果。",
		"voice_file": "VOICE_MAIN_007_017_01004",
		"still_path_hash": "7725975117834676314",
		"speech_balloon_type_id": 780292254
	},
	{
		"id": 9,
		"localized_name": "克莉赛尔达",
		"romanized_name": "Criselda",
		"model_path_hash": "2319149981238984606",
		"text": "呵呵，有了这个，“那个”就能接近完全体了。",
		"voice_file": "VOICE_MAIN_008_017_01005",
		"still_path_hash": "2415369427152481317",
		"speech_balloon_type_id": 780292254
	},
	{
		"id": 10,
		"localized_name": "克莉赛尔达",
		"romanized_name": "Criselda",
		"model_path_hash": "2319149981238984606",
		"text": "马上开始着手调整吧。\n能麻烦你也通知安洁一声吗？",
		"voice_file": "VOICE_MAIN_008_017_01006",
		"still_path_hash": "2415369427152481317",
		"speech_balloon_type_id": 780292254
	},
	{
		"id": 11,
		"localized_name": "瓦尔特",
		"romanized_name": "Walther",
		"model_path_hash": "8090265573840748859",
		"text": "好的。",
		"voice_file": "VOICE_MAIN_007_017_01007",
		"still_path_hash": "7725975117834676314",
		"speech_balloon_type_id": 780292254
	},
	{
		"id": 12,
		"localized_name": "瓦莱莉娅",
		"romanized_name": "Valeria",
		"model_path_hash": "4979147540429202173",
		"text": "唉……",
		"voice_file": "VOICE_MAIN_002_017_01008",
		"still_path_hash": "7558252374860649663",
		"speech_balloon_type_id": 780292254
	},
	{
		"id": 13,
		"localized_name": "瓦莱莉娅",
		"romanized_name": "Valeria",
		"model_path_hash": "0",
		"text": "（……克莉赛尔达说过，等人造顶兽一战结束后，\n　就会把事情都告诉我。）",
		"voice_file": "VOICE_MAIN_002_017_01009",
		"still_path_hash": "7558252374860649663",
		"speech_balloon_type_id": 780292254
	},
	{
		"id": 14,
		"localized_name": "瓦莱莉娅",
		"romanized_name": "Valeria",
		"model_path_hash": "0",
		"text": "（但现在她下落不明。\n　我还有很多事想问她、想当面说清楚……）",
		"voice_file": "VOICE_MAIN_002_017_01010",
		"still_path_hash": "7558252374860649663",
		"speech_balloon_type_id": 780292254
	},
	{
		"id": 15,
		"localized_name": "瓦莱莉娅",
		"romanized_name": "Valeria",
		"model_path_hash": "4979147540429202173",
		"text": "果然还是得我去找她——",
		"voice_file": "VOICE_MAIN_002_017_01011",
		"still_path_hash": "7558252374860649663",
		"speech_balloon_type_id": 780292254
	},
	{
		"id": 16,
		"localized_name": "瓦莱莉娅",
		"romanized_name": "Valeria",
		"model_path_hash": "4979147540429202173",
		"text": "……咦？",
		"voice_file": "VOICE_MAIN_002_017_01012",
		"still_path_hash": "7558252374860649663",
		"speech_balloon_type_id": 780292254
	},
	{
		"id": 17,
		"localized_name": "芙洛可",
		"romanized_name": "Flocke",
		"model_path_hash": "2379791261939253229",
		"text": "饭好了！",
		"voice_file": "VOICE_MAIN_052_017_01013",
		"still_path_hash": "1324369732733195994",
		"speech_balloon_type_id": 780292254
	},
	{
		"id": 18,
		"localized_name": "兰泽",
		"romanized_name": "Lanze",
		"model_path_hash": "845404123422268284",
		"text": "哦！终于能吃饭了！\n嗯……？说起来，瓦莱莉娅还没回来吗？",
		"voice_file": "VOICE_MAIN_053_017_01014",
		"still_path_hash": "5409134969144639524",
		"speech_balloon_type_id": 780292254
	},
	{
		"id": 19,
		"localized_name": "海蒂",
		"romanized_name": "Heidi",
		"model_path_hash": "5270784299656074783",
		"text": "是不是又在外面乱逛了？\n不过她闻到饭香味就会马上回来的吧。",
		"voice_file": "VOICE_MAIN_051_017_01015",
		"still_path_hash": "120518867847693403",
		"speech_balloon_type_id": 780292254
	},
	{
		"id": 20,
		"localized_name": "芙洛可",
		"romanized_name": "Flocke",
		"model_path_hash": "2379791261939253229",
		"text": "呵呵。那等到瓦莱莉娅小姐回来了再开饭吧。",
		"voice_file": "VOICE_MAIN_052_017_01016",
		"still_path_hash": "1324369732733195994",
		"speech_balloon_type_id": 780292254
	}
]