[
	{
		"id": 0,
		"localized_name": "Resna",
		"romanized_name": "Resna",
		"model_path_hash": "8643265264907274754",
		"text": "Eek!",
		"voice_file": "VOICE_MAIN_001_012_01025",
		"still_path_hash": "3572566872346296899",
		"speech_balloon_type_id": 780292254
	},
	{
		"id": 1,
		"localized_name": "Escha",
		"romanized_name": "Escha",
		"model_path_hash": "4942920317009730088",
		"text": "It's a sandstorm! Everyone, look out!",
		"voice_file": "VOICE_MAIN_028_012_01026",
		"still_path_hash": "8567200502263774699",
		"speech_balloon_type_id": 780292254
	},
	{
		"id": 2,
		"localized_name": "Izana",
		"romanized_name": "Izana",
		"model_path_hash": "3955217441086782382",
		"text": "Of all times!",
		"voice_file": "VOICE_MAIN_048_012_01027",
		"still_path_hash": "8711233837385589208",
		"speech_balloon_type_id": 780292254
	},
	{
		"id": 3,
		"localized_name": "Lara",
		"romanized_name": "Lara",
		"model_path_hash": "3588495634505174118",
		"text": "I believe we're finished here.",
		"voice_file": "VOICE_MAIN_005_012_01028",
		"still_path_hash": "1328706129982295513",
		"speech_balloon_type_id": 780292254
	},
	{
		"id": 4,
		"localized_name": "Geron",
		"romanized_name": "Geron",
		"model_path_hash": "7036248754503774915",
		"text": "Let's go.",
		"voice_file": "VOICE_MAIN_003_012_01029",
		"still_path_hash": "6398968499954469286",
		"speech_balloon_type_id": 780292254
	},
	{
		"id": 5,
		"localized_name": "Sophie",
		"romanized_name": "Sophie",
		"model_path_hash": "1747704331216962355",
		"text": "Ah! They're getting away!",
		"voice_file": "VOICE_MAIN_030_012_01030",
		"still_path_hash": "3373470695039518718",
		"speech_balloon_type_id": 780292254
	},
	{
		"id": 6,
		"localized_name": "Resna",
		"romanized_name": "Resna",
		"model_path_hash": "8643265264907274754",
		"text": "Wait—",
		"voice_file": "VOICE_MAIN_001_012_01031",
		"still_path_hash": "3572566872346296899",
		"speech_balloon_type_id": 780292254
	},
	{
		"id": 7,
		"localized_name": "Resna",
		"romanized_name": "Resna",
		"model_path_hash": "8643265264907274754",
		"text": "Is it really so impossible for us to understand each other? I feel like I never know what to say...",
		"voice_file": "VOICE_MAIN_001_012_01032",
		"still_path_hash": "3572566872346296899",
		"speech_balloon_type_id": 780292254
	},
	{
		"id": 8,
		"localized_name": "Sophie",
		"romanized_name": "Sophie",
		"model_path_hash": "1747704331216962355",
		"text": "Chin up, Resna. It hasn't been all bad, eh?",
		"voice_file": "VOICE_MAIN_030_012_01033",
		"still_path_hash": "3373470695039518718",
		"speech_balloon_type_id": 780292254
	},
	{
		"id": 9,
		"localized_name": "Sophie",
		"romanized_name": "Sophie",
		"model_path_hash": "1747704331216962355",
		"text": "You did a great job with your request, didn't you?",
		"voice_file": "VOICE_MAIN_030_012_01034",
		"still_path_hash": "3373470695039518718",
		"speech_balloon_type_id": 780292254
	},
	{
		"id": 10,
		"localized_name": "Resna",
		"romanized_name": "Resna",
		"model_path_hash": "8643265264907274754",
		"text": "Sophie...",
		"voice_file": "VOICE_MAIN_001_012_01035",
		"still_path_hash": "3572566872346296899",
		"speech_balloon_type_id": 780292254
	},
	{
		"id": 11,
		"localized_name": "Sophie",
		"romanized_name": "Sophie",
		"model_path_hash": "1747704331216962355",
		"text": "And your client was really impressed with your work!",
		"voice_file": "VOICE_MAIN_030_012_01036",
		"still_path_hash": "3373470695039518718",
		"speech_balloon_type_id": 780292254
	},
	{
		"id": 12,
		"localized_name": "Sophie",
		"romanized_name": "Sophie",
		"model_path_hash": "1747704331216962355",
		"text": "When your clothes go on sale, I'm sure they'll make the people living in the desert really happy.",
		"voice_file": "VOICE_MAIN_030_012_01037",
		"still_path_hash": "3373470695039518718",
		"speech_balloon_type_id": 780292254
	},
	{
		"id": 13,
		"localized_name": "Resna",
		"romanized_name": "Resna",
		"model_path_hash": "8643265264907274754",
		"text": "...You're right!",
		"voice_file": "VOICE_MAIN_001_012_01038",
		"still_path_hash": "3572566872346296899",
		"speech_balloon_type_id": 780292254
	}
]