[
	{
		"id": 0,
		"localized_name": "蘿樂娜",
		"romanized_name": "Rorona",
		"model_path_hash": "4482406372396026577",
		"text": "啊，歡迎回來～！",
		"voice_file": "VOICE_MAIN_018_001_00388",
		"still_path_hash": "6911172049205438765",
		"speech_balloon_type_id": 780292254
	},
	{
		"id": 1,
		"localized_name": "蕾斯娜",
		"romanized_name": "Resna",
		"model_path_hash": "8643265264907274754",
		"text": "那個，我把委託的東西帶來了。\n接下來這個該怎麼處理……",
		"voice_file": "VOICE_MAIN_001_001_00389",
		"still_path_hash": "3572566872346296899",
		"speech_balloon_type_id": 780292254
	},
	{
		"id": 2,
		"localized_name": "蘿樂娜",
		"romanized_name": "Rorona",
		"model_path_hash": "4482406372396026577",
		"text": "那麼，請先到櫃檯去吧～",
		"voice_file": "VOICE_MAIN_018_001_00390",
		"still_path_hash": "6911172049205438765",
		"speech_balloon_type_id": 780292254
	},
	{
		"id": 3,
		"localized_name": "萊莎",
		"romanized_name": "Ryza",
		"model_path_hash": "6459971860569016995",
		"text": "好，拿到這裡來。",
		"voice_file": "VOICE_MAIN_039_001_00391",
		"still_path_hash": "633958553226542878",
		"speech_balloon_type_id": 780292254
	},
	{
		"id": 4,
		"localized_name": "蕾斯娜",
		"romanized_name": "Resna",
		"model_path_hash": "8643265264907274754",
		"text": "對哦，萊莎前輩就是負責受理委託的啊！",
		"voice_file": "VOICE_MAIN_001_001_00392",
		"still_path_hash": "3572566872346296899",
		"speech_balloon_type_id": 780292254
	},
	{
		"id": 5,
		"localized_name": "萊莎",
		"romanized_name": "Ryza",
		"model_path_hash": "6459971860569016995",
		"text": "嗯，所以不必再查看了，妳合格啦！\n然後只要在這裡簽個名……",
		"voice_file": "VOICE_MAIN_039_001_00393",
		"still_path_hash": "633958553226542878",
		"speech_balloon_type_id": 780292254
	},
	{
		"id": 6,
		"localized_name": "伊克賽爾",
		"romanized_name": "Iksel",
		"model_path_hash": "8416193151802436544",
		"text": "各位！有緊急委託！",
		"voice_file": "VOICE_MAIN_020_001_00394",
		"still_path_hash": "8827427841789589118",
		"speech_balloon_type_id": 780292254
	},
	{
		"id": 7,
		"localized_name": "蕾斯娜",
		"romanized_name": "Resna",
		"model_path_hash": "8643265264907274754",
		"text": "哇，怎麼了呢？",
		"voice_file": "VOICE_MAIN_001_001_00395",
		"still_path_hash": "3572566872346296899",
		"speech_balloon_type_id": 780292254
	},
	{
		"id": 8,
		"localized_name": "伊克賽爾",
		"romanized_name": "Iksel",
		"model_path_hash": "8416193151802436544",
		"text": "附近的街道出現了魔物，\n有個商隊好像被困住了。",
		"voice_file": "VOICE_MAIN_020_001_00396",
		"still_path_hash": "8827427841789589118",
		"speech_balloon_type_id": 780292254
	},
	{
		"id": 9,
		"localized_name": "伊克賽爾",
		"romanized_name": "Iksel",
		"model_path_hash": "8416193151802436544",
		"text": "國家直接委託我們，希望有人能協助討伐魔物。\n能麻煩妳們快點趕過去嗎？",
		"voice_file": "VOICE_MAIN_020_001_00397",
		"still_path_hash": "8827427841789589118",
		"speech_balloon_type_id": 780292254
	},
	{
		"id": 10,
		"localized_name": "蕾斯娜",
		"romanized_name": "Resna",
		"model_path_hash": "8643265264907274754",
		"text": "好、我知道了！",
		"voice_file": "VOICE_MAIN_001_001_00398",
		"still_path_hash": "3572566872346296899",
		"speech_balloon_type_id": 780292254
	},
	{
		"id": 11,
		"localized_name": "萊莎",
		"romanized_name": "Ryza",
		"model_path_hash": "6459971860569016995",
		"text": "大家才剛回來，可能會感覺有點吃不消，\n但還是去把魔物收拾乾淨吧！",
		"voice_file": "VOICE_MAIN_039_001_00399",
		"still_path_hash": "633958553226542878",
		"speech_balloon_type_id": 780292254
	}
]