[
	{
		"id": 0,
		"localized_name": "伊札娜",
		"romanized_name": "Izana",
		"model_path_hash": "3955217441086782382",
		"text": "薩絲琪亞她也不用把話說得那麼嚴厲吧。",
		"voice_file": "VOICE_MAIN_048_002_00545",
		"still_path_hash": "8711233837385589208",
		"speech_balloon_type_id": 780292254
	},
	{
		"id": 1,
		"localized_name": "蕾斯娜",
		"romanized_name": "Resna",
		"model_path_hash": "0",
		"text": "…………",
		"voice_file": "VOICE_MAIN_001_002_00546",
		"still_path_hash": "3572566872346296899",
		"speech_balloon_type_id": 780292254
	},
	{
		"id": 2,
		"localized_name": "伊札娜",
		"romanized_name": "Izana",
		"model_path_hash": "3955217441086782382",
		"text": "……對了！等一下過來我家吧！\n我們開個作戰會議！",
		"voice_file": "VOICE_MAIN_048_002_00547",
		"still_path_hash": "8711233837385589208",
		"speech_balloon_type_id": 780292254
	},
	{
		"id": 3,
		"localized_name": "蕾斯娜",
		"romanized_name": "Resna",
		"model_path_hash": "8643265264907274754",
		"text": "好……",
		"voice_file": "VOICE_MAIN_001_002_00548",
		"still_path_hash": "3572566872346296899",
		"speech_balloon_type_id": 780292254
	},
	{
		"id": 4,
		"localized_name": "伊札娜的朋友A",
		"romanized_name": "",
		"model_path_hash": "0",
		"text": "啊──！伊札娜！\n好久不見！妳回來了啊。",
		"voice_file": "VOICE_MAIN_509_002_00549",
		"still_path_hash": "0",
		"speech_balloon_type_id": 780292254
	},
	{
		"id": 5,
		"localized_name": "伊札娜",
		"romanized_name": "Izana",
		"model_path_hash": "3955217441086782382",
		"text": "嗯！好久不見！",
		"voice_file": "VOICE_MAIN_048_002_00550",
		"still_path_hash": "8711233837385589208",
		"speech_balloon_type_id": 780292254
	},
	{
		"id": 6,
		"localized_name": "伊札娜的朋友B",
		"romanized_name": "",
		"model_path_hash": "0",
		"text": "對了對了，有伴手禮嗎？",
		"voice_file": "VOICE_MAIN_510_002_00551",
		"still_path_hash": "0",
		"speech_balloon_type_id": 780292254
	},
	{
		"id": 7,
		"localized_name": "伊札娜的朋友A",
		"romanized_name": "",
		"model_path_hash": "0",
		"text": "喂喂，妳也太厚臉皮了吧。",
		"voice_file": "VOICE_MAIN_509_002_00552",
		"still_path_hash": "0",
		"speech_balloon_type_id": 780292254
	},
	{
		"id": 8,
		"localized_name": "伊札娜的朋友B",
		"romanized_name": "",
		"model_path_hash": "0",
		"text": "咦～可是王都的伴手禮很令人好奇嘛。",
		"voice_file": "VOICE_MAIN_510_002_00553",
		"still_path_hash": "0",
		"speech_balloon_type_id": 780292254
	},
	{
		"id": 9,
		"localized_name": "伊札娜",
		"romanized_name": "Izana",
		"model_path_hash": "3955217441086782382",
		"text": "帶了帶了！大家的份我早就準備好了啦！",
		"voice_file": "VOICE_MAIN_048_002_00554",
		"still_path_hash": "8711233837385589208",
		"speech_balloon_type_id": 780292254
	},
	{
		"id": 10,
		"localized_name": "伊札娜的朋友A",
		"romanized_name": "",
		"model_path_hash": "0",
		"text": "哦，真不愧是妳！\n欸，大家都在那邊呢，快過去吧。",
		"voice_file": "VOICE_MAIN_509_002_00555",
		"still_path_hash": "0",
		"speech_balloon_type_id": 780292254
	},
	{
		"id": 11,
		"localized_name": "伊札娜",
		"romanized_name": "Izana",
		"model_path_hash": "3955217441086782382",
		"text": "嗯！蕾斯娜也一起來吧！",
		"voice_file": "VOICE_MAIN_048_002_00556",
		"still_path_hash": "8711233837385589208",
		"speech_balloon_type_id": 780292254
	},
	{
		"id": 12,
		"localized_name": "蕾斯娜",
		"romanized_name": "Resna",
		"model_path_hash": "8643265264907274754",
		"text": "啊……不用了！我就不過去了。",
		"voice_file": "VOICE_MAIN_001_002_00557",
		"still_path_hash": "3572566872346296899",
		"speech_balloon_type_id": 780292254
	},
	{
		"id": 13,
		"localized_name": "伊札娜",
		"romanized_name": "Izana",
		"model_path_hash": "3955217441086782382",
		"text": "咦？可是……",
		"voice_file": "VOICE_MAIN_048_002_00558",
		"still_path_hash": "8711233837385589208",
		"speech_balloon_type_id": 780292254
	},
	{
		"id": 14,
		"localized_name": "蕾斯娜",
		"romanized_name": "Resna",
		"model_path_hash": "8643265264907274754",
		"text": "我必須把今天師父告訴我的事情整理成筆記！\n為了課題還得研究一下對策！妳就自己去吧，好嗎？",
		"voice_file": "VOICE_MAIN_001_002_00559",
		"still_path_hash": "3572566872346296899",
		"speech_balloon_type_id": 780292254
	},
	{
		"id": 15,
		"localized_name": "伊札娜",
		"romanized_name": "Izana",
		"model_path_hash": "3955217441086782382",
		"text": "嗯，那好吧，晚點見哦。",
		"voice_file": "VOICE_MAIN_048_002_00560",
		"still_path_hash": "8711233837385589208",
		"speech_balloon_type_id": 780292254
	}
]