[
	{
		"id": 0,
		"localized_name": "Resna",
		"romanized_name": "Resna",
		"model_path_hash": "8643265264907274754",
		"text": "First things first, I'm terribly sorry for not keeping in better touch. It's been a while since we've really spoken, hasn't it?",
		"voice_file": "VOICE_MAIN_001_018_00895",
		"still_path_hash": "3572566872346296899",
		"speech_balloon_type_id": 780292254
	},
	{
		"id": 1,
		"localized_name": "Keithgriff",
		"romanized_name": "Keithgriff",
		"model_path_hash": "703841452402553687",
		"text": "Yes, you would have still been an apprentice. Though, I've heard your name mentioned by people across the continent since then.",
		"voice_file": "VOICE_MAIN_026_018_00896",
		"still_path_hash": "8911695089895149925",
		"speech_balloon_type_id": 780292254
	},
	{
		"id": 2,
		"localized_name": "Resna",
		"romanized_name": "Resna",
		"model_path_hash": "8643265264907274754",
		"text": "Th-That's good! I've been traveling around to try and prepare for a journey to the World's End.",
		"voice_file": "VOICE_MAIN_001_018_00897",
		"still_path_hash": "3572566872346296899",
		"speech_balloon_type_id": 780292254
	},
	{
		"id": 3,
		"localized_name": "Keithgriff",
		"romanized_name": "Keithgriff",
		"model_path_hash": "703841452402553687",
		"text": "I see. I've been making a similar trek. Now, I have to ask...",
		"voice_file": "VOICE_MAIN_026_018_00898",
		"still_path_hash": "8911695089895149925",
		"speech_balloon_type_id": 780292254
	},
	{
		"id": 4,
		"localized_name": "Keithgriff",
		"romanized_name": "Keithgriff",
		"model_path_hash": "703841452402553687",
		"text": "You are aware of the various towns and villages that exist outside of Lantarna's borders, correct?",
		"voice_file": "VOICE_MAIN_026_018_00899",
		"still_path_hash": "8911695089895149925",
		"speech_balloon_type_id": 780292254
	},
	{
		"id": 5,
		"localized_name": "Resna",
		"romanized_name": "Resna",
		"model_path_hash": "8643265264907274754",
		"text": "Well, yes, I am. An Apexi lives in the waters around there, so it's pretty much impossible to investigate that area, but...",
		"voice_file": "VOICE_MAIN_001_018_00900",
		"still_path_hash": "3572566872346296899",
		"speech_balloon_type_id": 780292254
	},
	{
		"id": 6,
		"localized_name": "Resna",
		"romanized_name": "Resna",
		"model_path_hash": "8643265264907274754",
		"text": "What we do know is that there's an archipelago that stretches out from the northwest called the Infinite Island Chain.",
		"voice_file": "VOICE_MAIN_001_018_00901",
		"still_path_hash": "3572566872346296899",
		"speech_balloon_type_id": 780292254
	},
	{
		"id": 7,
		"localized_name": "Resna",
		"romanized_name": "Resna",
		"model_path_hash": "8643265264907274754",
		"text": "Legend has it that if you follow that, it will lead you to the World's End.",
		"voice_file": "VOICE_MAIN_001_018_00902",
		"still_path_hash": "3572566872346296899",
		"speech_balloon_type_id": 780292254
	},
	{
		"id": 8,
		"localized_name": "Keithgriff",
		"romanized_name": "Keithgriff",
		"model_path_hash": "703841452402553687",
		"text": "Hm... While that does appear to be the most widespread theory, I've come across a legend that claims otherwise.",
		"voice_file": "VOICE_MAIN_026_018_00903",
		"still_path_hash": "8911695089895149925",
		"speech_balloon_type_id": 780292254
	},
	{
		"id": 9,
		"localized_name": "Resna",
		"romanized_name": "Resna",
		"model_path_hash": "8643265264907274754",
		"text": "Oh! What does it say?",
		"voice_file": "VOICE_MAIN_001_018_00904",
		"still_path_hash": "3572566872346296899",
		"speech_balloon_type_id": 780292254
	},
	{
		"id": 10,
		"localized_name": "Keithgriff",
		"romanized_name": "Keithgriff",
		"model_path_hash": "703841452402553687",
		"text": "It says that what lies there is not the World's End, but the Realm of Oblivion.",
		"voice_file": "VOICE_MAIN_026_018_00905",
		"still_path_hash": "8911695089895149925",
		"speech_balloon_type_id": 780292254
	},
	{
		"id": 11,
		"localized_name": "Roman",
		"romanized_name": "Roman",
		"model_path_hash": "8999309826977301995",
		"text": "Right, the one that claims nothing's at the edge of the world but darkness. Apparently, the only thing that awaits people there is every kind of horror imaginable.",
		"voice_file": "VOICE_MAIN_049_018_00906",
		"still_path_hash": "1098656846957192188",
		"speech_balloon_type_id": 780292254
	},
	{
		"id": 12,
		"localized_name": "Keithgriff",
		"romanized_name": "Keithgriff",
		"model_path_hash": "703841452402553687",
		"text": "Hmph. Good to see that the members of Lantarna's royal family are keeping up with their lore.",
		"voice_file": "VOICE_MAIN_026_018_00907",
		"still_path_hash": "8911695089895149925",
		"speech_balloon_type_id": 780292254
	},
	{
		"id": 13,
		"localized_name": "Resna",
		"romanized_name": "Resna",
		"model_path_hash": "8643265264907274754",
		"text": "Y-You knew about that?!",
		"voice_file": "VOICE_MAIN_001_018_00908",
		"still_path_hash": "3572566872346296899",
		"speech_balloon_type_id": 780292254
	},
	{
		"id": 14,
		"localized_name": "Roman",
		"romanized_name": "Roman",
		"model_path_hash": "8999309826977301995",
		"text": "Ultimately, a legend's just another kind of rumor. However, that one offers no hope or comfort, so it's not the sort of thing you'd want to have spreading through a kingdom.",
		"voice_file": "VOICE_MAIN_049_018_00909",
		"still_path_hash": "1098656846957192188",
		"speech_balloon_type_id": 780292254
	},
	{
		"id": 15,
		"localized_name": "Izana",
		"romanized_name": "Izana",
		"model_path_hash": "760867264549063535",
		"text": "I never realized you were so considerate, Roman.",
		"voice_file": "VOICE_MAIN_048_018_00910",
		"still_path_hash": "8252366596791600256",
		"speech_balloon_type_id": 780292254
	},
	{
		"id": 16,
		"localized_name": "Keithgriff",
		"romanized_name": "Keithgriff",
		"model_path_hash": "703841452402553687",
		"text": "Whether or not it is of any concern to the kingdom is irrelevant.",
		"voice_file": "VOICE_MAIN_026_018_00911",
		"still_path_hash": "8911695089895149925",
		"speech_balloon_type_id": 780292254
	},
	{
		"id": 17,
		"localized_name": "Keithgriff",
		"romanized_name": "Keithgriff",
		"model_path_hash": "703841452402553687",
		"text": "My concern is whether this twisted world of day and night is the result of some man-made contrivance.",
		"voice_file": "VOICE_MAIN_026_018_00912",
		"still_path_hash": "8911695089895149925",
		"speech_balloon_type_id": 780292254
	},
	{
		"id": 18,
		"localized_name": "Resna",
		"romanized_name": "Resna",
		"model_path_hash": "8643265264907274754",
		"text": "Oh, right! All the wanderers keep saying that they have other times of day in their worlds.",
		"voice_file": "VOICE_MAIN_001_018_00913",
		"still_path_hash": "3572566872346296899",
		"speech_balloon_type_id": 780292254
	},
	{
		"id": 19,
		"localized_name": "Johanna",
		"romanized_name": "Johanna",
		"model_path_hash": "4318551206560057077",
		"text": "Wait, what?",
		"voice_file": "VOICE_MAIN_004_018_00914",
		"still_path_hash": "125453364659396444",
		"speech_balloon_type_id": 780292254
	},
	{
		"id": 20,
		"localized_name": "Judie",
		"romanized_name": "Judie",
		"model_path_hash": "2697025160672431728",
		"text": "In my world, the sun appears at one end of the horizon, then sets on the other side.",
		"voice_file": "VOICE_MAIN_014_018_00915",
		"still_path_hash": "2032894617718182411",
		"speech_balloon_type_id": 780292254
	},
	{
		"id": 21,
		"localized_name": "Judie",
		"romanized_name": "Judie",
		"model_path_hash": "2697025160672431728",
		"text": "That means there are stretches of time between noon and night, and vice versa. We call those \"morning\" and \"evening.\"",
		"voice_file": "VOICE_MAIN_014_018_00916",
		"still_path_hash": "2032894617718182411",
		"speech_balloon_type_id": 780292254
	},
	{
		"id": 22,
		"localized_name": "Judie",
		"romanized_name": "Judie",
		"model_path_hash": "2697025160672431728",
		"text": "Honestly, I still haven't gotten used to the fact that it'll be high noon one minute, and the middle of the night the next.",
		"voice_file": "VOICE_MAIN_014_018_00917",
		"still_path_hash": "2032894617718182411",
		"speech_balloon_type_id": 780292254
	},
	{
		"id": 23,
		"localized_name": "Johanna",
		"romanized_name": "Johanna",
		"model_path_hash": "4318551206560057077",
		"text": "You're the weird one.",
		"voice_file": "VOICE_MAIN_004_018_00918",
		"still_path_hash": "125453364659396444",
		"speech_balloon_type_id": 780292254
	},
	{
		"id": 24,
		"localized_name": "Keithgriff",
		"romanized_name": "Keithgriff",
		"model_path_hash": "703841452402553687",
		"text": "I've spoken with the other wanderers, and by and large, that appears to be the natural way of things. However, for some reason, this world eschews convention.",
		"voice_file": "VOICE_MAIN_026_018_00919",
		"still_path_hash": "8911695089895149925",
		"speech_balloon_type_id": 780292254
	},
	{
		"id": 25,
		"localized_name": "Keithgriff",
		"romanized_name": "Keithgriff",
		"model_path_hash": "703841452402553687",
		"text": "That blatant disregard of the established order is likely due to an absurd event that happened in the distant past, much like in my own world.",
		"voice_file": "VOICE_MAIN_026_018_00920",
		"still_path_hash": "8911695089895149925",
		"speech_balloon_type_id": 780292254
	},
	{
		"id": 26,
		"localized_name": "Keithgriff",
		"romanized_name": "Keithgriff",
		"model_path_hash": "703841452402553687",
		"text": "Presumably, proof of this must exist. While some of those answers may come from surveys of ruins from the Nebra civilization, most will likely require a departure from the continent.",
		"voice_file": "VOICE_MAIN_026_018_00921",
		"still_path_hash": "8911695089895149925",
		"speech_balloon_type_id": 780292254
	},
	{
		"id": 27,
		"localized_name": "Resna",
		"romanized_name": "Resna",
		"model_path_hash": "8643265264907274754",
		"text": "Actually, that's exactly what I wanted to talk to you about.",
		"voice_file": "VOICE_MAIN_001_018_00922",
		"still_path_hash": "3572566872346296899",
		"speech_balloon_type_id": 780292254
	},
	{
		"id": 28,
		"localized_name": "Keithgriff",
		"romanized_name": "Keithgriff",
		"model_path_hash": "703841452402553687",
		"text": "Oh?",
		"voice_file": "VOICE_MAIN_026_018_00923",
		"still_path_hash": "8911695089895149925",
		"speech_balloon_type_id": 780292254
	},
	{
		"id": 29,
		"localized_name": "Resna",
		"romanized_name": "Resna",
		"model_path_hash": "8643265264907274754",
		"text": "Criselda, the leader of the Polar Night Alchemists, mentioned it before.",
		"voice_file": "VOICE_MAIN_001_018_00924",
		"still_path_hash": "3572566872346296899",
		"speech_balloon_type_id": 780292254
	},
	{
		"id": 30,
		"localized_name": "Resna",
		"romanized_name": "Resna",
		"model_path_hash": "8643265264907274754",
		"text": "That we've somehow accepted the idea that there are things in this world that just can't be explained.",
		"voice_file": "VOICE_MAIN_001_018_00925",
		"still_path_hash": "3572566872346296899",
		"speech_balloon_type_id": 780292254
	},
	{
		"id": 31,
		"localized_name": "Resna",
		"romanized_name": "Resna",
		"model_path_hash": "8643265264907274754",
		"text": "So I was wondering if maybe that had something to do with what you were researching.",
		"voice_file": "VOICE_MAIN_001_018_00926",
		"still_path_hash": "3572566872346296899",
		"speech_balloon_type_id": 780292254
	},
	{
		"id": 32,
		"localized_name": "Keithgriff",
		"romanized_name": "Keithgriff",
		"model_path_hash": "703841452402553687",
		"text": "I see. Well, you aren't entirely incorrect. After all...",
		"voice_file": "VOICE_MAIN_026_018_00927",
		"still_path_hash": "8911695089895149925",
		"speech_balloon_type_id": 780292254
	},
	{
		"id": 33,
		"localized_name": "Keithgriff",
		"romanized_name": "Keithgriff",
		"model_path_hash": "703841452402553687",
		"text": "That same leader took the trouble to seek me out directly. It was precisely during that mass attack against the other wanderers.",
		"voice_file": "VOICE_MAIN_026_018_00928",
		"still_path_hash": "8911695089895149925",
		"speech_balloon_type_id": 780292254
	},
	{
		"id": 34,
		"localized_name": "Resna",
		"romanized_name": "Resna",
		"model_path_hash": "8643265264907274754",
		"text": "S-She did?!",
		"voice_file": "VOICE_MAIN_001_018_00929",
		"still_path_hash": "3572566872346296899",
		"speech_balloon_type_id": 780292254
	},
	{
		"id": 35,
		"localized_name": "Keithgriff",
		"romanized_name": "Keithgriff",
		"model_path_hash": "703841452402553687",
		"text": "Your mentor also happened to appear at the same time.",
		"voice_file": "VOICE_MAIN_026_018_00930",
		"still_path_hash": "8911695089895149925",
		"speech_balloon_type_id": 780292254
	},
	{
		"id": 36,
		"localized_name": "Resna",
		"romanized_name": "Resna",
		"model_path_hash": "8643265264907274754",
		"text": "Huh?! Miss Saskia did?!",
		"voice_file": "VOICE_MAIN_001_018_00931",
		"still_path_hash": "3572566872346296899",
		"speech_balloon_type_id": 780292254
	},
	{
		"id": 37,
		"localized_name": "Keithgriff",
		"romanized_name": "Keithgriff",
		"model_path_hash": "703841452402553687",
		"text": "We spoke with that leader, who claimed that my desires were mostly in line with her own.",
		"voice_file": "VOICE_MAIN_026_018_00932",
		"still_path_hash": "8911695089895149925",
		"speech_balloon_type_id": 780292254
	},
	{
		"id": 38,
		"localized_name": "Resna",
		"romanized_name": "Resna",
		"model_path_hash": "8643265264907274754",
		"text": "So...what is it that Criselda wants?",
		"voice_file": "VOICE_MAIN_001_018_00933",
		"still_path_hash": "3572566872346296899",
		"speech_balloon_type_id": 780292254
	},
	{
		"id": 39,
		"localized_name": "Keithgriff",
		"romanized_name": "Keithgriff",
		"model_path_hash": "703841452402553687",
		"text": "That I could not say. We fought, but it didn't amount to much. She quickly slipped away.",
		"voice_file": "VOICE_MAIN_026_018_00934",
		"still_path_hash": "8911695089895149925",
		"speech_balloon_type_id": 780292254
	},
	{
		"id": 40,
		"localized_name": "Keithgriff",
		"romanized_name": "Keithgriff",
		"model_path_hash": "703841452402553687",
		"text": "However, one thing is certain—those Polar Night Alchemists have yet to exhaust all of their plans.",
		"voice_file": "VOICE_MAIN_026_018_00935",
		"still_path_hash": "8911695089895149925",
		"speech_balloon_type_id": 780292254
	},
	{
		"id": 41,
		"localized_name": "Resna",
		"romanized_name": "Resna",
		"model_path_hash": "8643265264907274754",
		"text": "Just what are they going to do next...?",
		"voice_file": "VOICE_MAIN_001_018_00936",
		"still_path_hash": "3572566872346296899",
		"speech_balloon_type_id": 780292254
	},
	{
		"id": 42,
		"localized_name": "Keithgriff",
		"romanized_name": "Keithgriff",
		"model_path_hash": "703841452402553687",
		"text": "Whatever you do, take care.",
		"voice_file": "VOICE_MAIN_026_018_00937",
		"still_path_hash": "8911695089895149925",
		"speech_balloon_type_id": 780292254
	},
	{
		"id": 43,
		"localized_name": "Judie",
		"romanized_name": "Judie",
		"model_path_hash": "2697025160672431728",
		"text": "H-Hey! Wait! Mr. Keith?!",
		"voice_file": "VOICE_MAIN_014_018_00938",
		"still_path_hash": "2032894617718182411",
		"speech_balloon_type_id": 780292254
	}
]