[
	{
		"id": 0,
		"localized_name": "克莉賽爾達",
		"romanized_name": "Criselda",
		"model_path_hash": "5977193608689657755",
		"text": "終於來了啊，真是讓我久等了。",
		"voice_file": "VOICE_MAIN_008_021_00627",
		"still_path_hash": "1369125961384061308",
		"speech_balloon_type_id": 780292254
	},
	{
		"id": 1,
		"localized_name": "安潔",
		"romanized_name": "Antje",
		"model_path_hash": "4143557775615003368",
		"text": "又是一群人蜂擁而來……",
		"voice_file": "VOICE_MAIN_006_021_00628",
		"still_path_hash": "3623196163129163432",
		"speech_balloon_type_id": 780292254
	},
	{
		"id": 2,
		"localized_name": "傑隆",
		"romanized_name": "Geron",
		"model_path_hash": "7036248754503774915",
		"text": "崖下似乎有連綿的尖銳岩石，\n小心別在戰鬥中掉下去。",
		"voice_file": "VOICE_MAIN_003_021_00629",
		"still_path_hash": "6398968499954469286",
		"speech_balloon_type_id": 780292254
	},
	{
		"id": 3,
		"localized_name": "拉拉",
		"romanized_name": "Lara",
		"model_path_hash": "2284298087769022650",
		"text": "我會注意的。",
		"voice_file": "VOICE_MAIN_005_021_00630",
		"still_path_hash": "1328706129982295513",
		"speech_balloon_type_id": 780292254
	},
	{
		"id": 4,
		"localized_name": "蕾斯娜",
		"romanized_name": "Resna",
		"model_path_hash": "8643265264907274754",
		"text": "克莉賽爾達小姐，我是接下妳的委託而來的。",
		"voice_file": "VOICE_MAIN_001_021_00631",
		"still_path_hash": "3572566872346296899",
		"speech_balloon_type_id": 780292254
	},
	{
		"id": 5,
		"localized_name": "克莉賽爾達",
		"romanized_name": "Criselda",
		"model_path_hash": "5977193608689657755",
		"text": "沒錯，既然我已經獲得期盼的力量，那就沒必要再逃。\n在這裡也不需要顧慮到其他人。",
		"voice_file": "VOICE_MAIN_008_021_00632",
		"still_path_hash": "1369125961384061308",
		"speech_balloon_type_id": 780292254
	},
	{
		"id": 6,
		"localized_name": "克莉賽爾達",
		"romanized_name": "Criselda",
		"model_path_hash": "5977193608689657755",
		"text": "讓我們徹底打到其中一方倒下為止吧。",
		"voice_file": "VOICE_MAIN_008_021_00633",
		"still_path_hash": "1369125961384061308",
		"speech_balloon_type_id": 780292254
	},
	{
		"id": 7,
		"localized_name": "瓦萊莉婭",
		"romanized_name": "Valeria",
		"model_path_hash": "4979147540429202173",
		"text": "雖然我個人並不討厭妳，\n但我不能原諒妳利用了失去理智的我。",
		"voice_file": "VOICE_MAIN_002_021_00634",
		"still_path_hash": "7558252374860649663",
		"speech_balloon_type_id": 780292254
	},
	{
		"id": 8,
		"localized_name": "海蒂",
		"romanized_name": "Heidi",
		"model_path_hash": "5270784299656074783",
		"text": "搭檔的敵人就是我的敵人。",
		"voice_file": "VOICE_MAIN_051_021_00635",
		"still_path_hash": "120518867847693403",
		"speech_balloon_type_id": 780292254
	},
	{
		"id": 9,
		"localized_name": "克莉賽爾達",
		"romanized_name": "Criselda",
		"model_path_hash": "5977193608689657755",
		"text": "哎呀，我可是很喜歡瓦萊莉婭的喔。",
		"voice_file": "VOICE_MAIN_008_021_00636",
		"still_path_hash": "1369125961384061308",
		"speech_balloon_type_id": 780292254
	},
	{
		"id": 10,
		"localized_name": "蕾斯娜",
		"romanized_name": "Resna",
		"model_path_hash": "7020965581047989271",
		"text": "不能再任妳為所欲為了，\n我要阻止妳。",
		"voice_file": "VOICE_MAIN_001_021_00637",
		"still_path_hash": "7541111968141087475",
		"speech_balloon_type_id": 780292254
	},
	{
		"id": 11,
		"localized_name": "克莉賽爾達",
		"romanized_name": "Criselda",
		"model_path_hash": "5977193608689657755",
		"text": "我很欣賞妳的這份決心。",
		"voice_file": "VOICE_MAIN_008_021_00638",
		"still_path_hash": "1369125961384061308",
		"speech_balloon_type_id": 780292254
	},
	{
		"id": 12,
		"localized_name": "安潔",
		"romanized_name": "Antje",
		"model_path_hash": "4143557775615003368",
		"text": "我也一起上。",
		"voice_file": "VOICE_MAIN_006_021_00639",
		"still_path_hash": "3623196163129163432",
		"speech_balloon_type_id": 780292254
	},
	{
		"id": 13,
		"localized_name": "安潔",
		"romanized_name": "Antje",
		"model_path_hash": "4143557775615003368",
		"text": "我會永遠在妳身旁，這是我們的約定……",
		"voice_file": "VOICE_MAIN_006_021_00640",
		"still_path_hash": "3623196163129163432",
		"speech_balloon_type_id": 780292254
	},
	{
		"id": 14,
		"localized_name": "克莉賽爾達",
		"romanized_name": "Criselda",
		"model_path_hash": "5977193608689657755",
		"text": "是啊，安潔。",
		"voice_file": "VOICE_MAIN_008_021_00641",
		"still_path_hash": "1369125961384061308",
		"speech_balloon_type_id": 780292254
	},
	{
		"id": 15,
		"localized_name": "蕾斯娜",
		"romanized_name": "Resna",
		"model_path_hash": "7020965581047989271",
		"text": "安潔……",
		"voice_file": "VOICE_MAIN_001_021_00642",
		"still_path_hash": "7541111968141087475",
		"speech_balloon_type_id": 780292254
	},
	{
		"id": 16,
		"localized_name": "約翰娜",
		"romanized_name": "Johanna",
		"model_path_hash": "4318551206560057077",
		"text": "不過……我也不是無法理解\n想要待在某人身邊的心情。",
		"voice_file": "VOICE_MAIN_004_021_00643",
		"still_path_hash": "125453364659396444",
		"speech_balloon_type_id": 780292254
	},
	{
		"id": 17,
		"localized_name": "伊札娜",
		"romanized_name": "Izana",
		"model_path_hash": "760867264549063535",
		"text": "明明彼此是敵對也一樣呢。",
		"voice_file": "VOICE_MAIN_048_021_00644",
		"still_path_hash": "8252366596791600256",
		"speech_balloon_type_id": 780292254
	},
	{
		"id": 18,
		"localized_name": "克莉賽爾達",
		"romanized_name": "Criselda",
		"model_path_hash": "5977193608689657755",
		"text": "瓦爾特。",
		"voice_file": "VOICE_MAIN_008_021_00645",
		"still_path_hash": "1369125961384061308",
		"speech_balloon_type_id": 780292254
	},
	{
		"id": 19,
		"localized_name": "瓦爾特",
		"romanized_name": "Walther",
		"model_path_hash": "6153875608616738871",
		"text": "唉……真是沒辦法。",
		"voice_file": "VOICE_MAIN_007_021_00646",
		"still_path_hash": "7725975117834676314",
		"speech_balloon_type_id": 780292254
	},
	{
		"id": 20,
		"localized_name": "瓦爾特",
		"romanized_name": "Walther",
		"model_path_hash": "6153875608616738871",
		"text": "雖然很想旁觀鍊金術士之間的戰鬥，\n但看來情況不容許我這麼做。",
		"voice_file": "VOICE_MAIN_007_021_00647",
		"still_path_hash": "7725975117834676314",
		"speech_balloon_type_id": 780292254
	},
	{
		"id": 21,
		"localized_name": "傑隆",
		"romanized_name": "Geron",
		"model_path_hash": "7036248754503774915",
		"text": "真沒想到你會對克莉賽爾達如此盡心盡力。",
		"voice_file": "VOICE_MAIN_003_021_00648",
		"still_path_hash": "6398968499954469286",
		"speech_balloon_type_id": 780292254
	},
	{
		"id": 22,
		"localized_name": "瓦爾特",
		"romanized_name": "Walther",
		"model_path_hash": "6153875608616738871",
		"text": "這是身為後輩的道義。\n而且既然要做，就要傾盡全力。",
		"voice_file": "VOICE_MAIN_007_021_00649",
		"still_path_hash": "7725975117834676314",
		"speech_balloon_type_id": 780292254
	},
	{
		"id": 23,
		"localized_name": "拉拉",
		"romanized_name": "Lara",
		"model_path_hash": "2284298087769022650",
		"text": "要來了！",
		"voice_file": "VOICE_MAIN_005_021_00650",
		"still_path_hash": "1328706129982295513",
		"speech_balloon_type_id": 780292254
	}
]